{
  "scraped_at": "2026-04-17T10:01:46.918626",
  "total_products": 25,
  "top_deals": [
    {
      "asin": "B0FSL2L7LW",
      "url": "https://www.amazon.fr/dp/B0FSL2L7LW",
      "title_preview": "",
      "price_flash": "Prix Flash: 299,98 €",
      "original_price": "Le plus bas : 999,99 €",
      "discount_text": "",
      "category": "Aspirateurs, entretien des sols et nettoyeurs de vitres",
      "has_prime": false,
      "title": "Lefant M3 Robot Aspirateur Laveur 12 000 Pa, Station Multifonctionnelle, Double Serpillière Rotative 200 TR/Min, Navigation dToF, Évitement d'obstacles PSD, 220min, 30 réglages de Niveau d'eau",
      "price": 299.98,
      "price_original": 999.99,
      "images": [
        "https://m.media-amazon.com/images/I/71i35ufWOXL._AC_SL1500_.jpg",
        "https://m.media-amazon.com/images/I/41q7yOd0YyL.jpg",
        "https://m.media-amazon.com/images/I/41G9RD2oc4L.jpg",
        "https://m.media-amazon.com/images/I/41Q2igEWjpL.jpg",
        "https://m.media-amazon.com/images/I/416l028hncL.jpg",
        "https://m.media-amazon.com/images/I/51wIsstigzL.jpg",
        "https://m.media-amazon.com/images/I/51H2s-fJbPL.jpg",
        "https://m.media-amazon.com/images/I/41i7pvoAzQL.jpg"
      ],
      "triggers": {
        "rating": 4.3,
        "reviews_count": 2607,
        "discount_percent": 70,
        "original_price": 999.99,
        "discount_amount": 700.01,
        "has_prime": true
      },
      "score": 7.5,
      "deal_number": 1,
      "deal_id": "#001"
    },
    {
      "asin": "B091GB1NP1",
      "url": "https://www.amazon.fr/dp/B091GB1NP1",
      "title_preview": "",
      "price_flash": "Prix Flash: 18,99 €",
      "original_price": "Le plus bas : 22,99 €",
      "discount_text": "",
      "category": "Vitamines, minéraux et compléments",
      "has_prime": false,
      "title": "Vitamine D3 K2 MK7, 365 Micro-Comprimés Végétariens (pour 1 An), Combinaison Vit D3 2000UI Cholécalciférol avec Vitamine K2 MK7 200μg Ménaquinone, sans Stéarate de Magnésium",
      "price": 18.99,
      "price_original": 22.99,
      "images": [
        "https://m.media-amazon.com/images/I/71dQNhLYgeL._AC_SL1500_.jpg",
        "https://m.media-amazon.com/images/I/41AdssjR5pL.jpg",
        "https://m.media-amazon.com/images/I/41lFe6LTfQL.jpg",
        "https://m.media-amazon.com/images/I/41+nkFa3CyL.jpg",
        "https://m.media-amazon.com/images/I/516H24Q0E8L.jpg",
        "https://m.media-amazon.com/images/I/51NPKIixE8L.jpg",
        "https://m.media-amazon.com/images/I/41OSJW1YJHL.jpg",
        "https://m.media-amazon.com/images/I/31pl4d8ydVL.jpg"
      ],
      "triggers": {
        "rating": 4.5,
        "reviews_count": 6417,
        "discount_percent": 17,
        "original_price": 22.99,
        "discount_amount": 4,
        "has_prime": true
      },
      "score": 7.0,
      "deal_number": 2,
      "deal_id": "#002"
    },
    {
      "asin": "B075JMFTB8",
      "url": "https://www.amazon.fr/dp/B075JMFTB8",
      "title_preview": "",
      "price_flash": "Prix Flash: 26,50 €",
      "original_price": "Le plus bas : 27,90 €",
      "discount_text": "",
      "category": "Ameublement et décoration",
      "has_prime": false,
      "title": "Utopia Bedding Couette 220x240 cm, Couette Chaud 370 GSM, pour lit 2 Personne, Couverture Blanc avec Onglets d'angle (Blanc)",
      "price": 26.5,
      "price_original": 27.9,
      "images": [
        "https://m.media-amazon.com/images/I/81MuXSwe-ZL._AC_SL1500_.jpg",
        "https://m.media-amazon.com/images/I/51i7V-2KJ7L.jpg",
        "https://m.media-amazon.com/images/I/31NP3zWi+QL.jpg",
        "https://m.media-amazon.com/images/I/41f5igACPML.jpg",
        "https://m.media-amazon.com/images/I/31Prnrf+rVL.jpg"
      ],
      "triggers": {
        "rating": 4.5,
        "reviews_count": 39434,
        "discount_percent": 5,
        "original_price": 27.9,
        "discount_amount": 1.4,
        "has_prime": true
      },
      "score": 7.0,
      "deal_number": 3,
      "deal_id": "#003"
    },
    {
      "asin": "B07CB94N28",
      "url": "https://www.amazon.fr/dp/B07CB94N28",
      "title_preview": "",
      "price_flash": "Prix Flash: 11,99 €",
      "original_price": "Le plus bas : 12,62 €",
      "discount_text": "",
      "category": "Ameublement et décoration",
      "has_prime": false,
      "title": "Utopia Bedding Drap Housse - Gris, 160 x 200 cm - Coupes de 35 cm pour Matelas épais - Polyester Microfibre brossée",
      "price": 11.99,
      "price_original": 12.62,
      "images": [
        "https://m.media-amazon.com/images/I/71k1qAeLoAL._AC_SL1500_.jpg",
        "https://m.media-amazon.com/images/I/41w1GUR+66L.jpg",
        "https://m.media-amazon.com/images/I/41FM-SawD0L.jpg",
        "https://m.media-amazon.com/images/I/41DuaiF+lZL.jpg",
        "https://m.media-amazon.com/images/I/41LfnP4PThL.jpg",
        "https://m.media-amazon.com/images/I/51+SnG-KPOL.jpg",
        "https://m.media-amazon.com/images/I/41FSLnmYy9L.jpg"
      ],
      "triggers": {
        "rating": 4.6,
        "reviews_count": 161412,
        "discount_percent": 5,
        "original_price": 12.62,
        "discount_amount": 0.63,
        "has_prime": true
      },
      "score": 7.0,
      "deal_number": 4,
      "deal_id": "#004"
    },
    {
      "asin": "B0CYPY3G8B",
      "url": "https://www.amazon.fr/dp/B0CYPY3G8B",
      "title_preview": "",
      "price_flash": "Prix Flash: 18,86 €",
      "original_price": "Le plus bas : 19,85 €",
      "discount_text": "",
      "category": "Ameublement et décoration",
      "has_prime": false,
      "title": "Utopia Bedding Housse De Matelas 140 x 190 x 20 cm Imperméable Avec Fermeture éclair, Certifié Oeko-TEX, Protégé Matelas, Blanc",
      "price": 18.86,
      "price_original": 19.85,
      "images": [
        "https://m.media-amazon.com/images/I/71-sHDrPc0L._AC_SL1500_.jpg",
        "https://m.media-amazon.com/images/I/41xQPZwIqQL.jpg",
        "https://m.media-amazon.com/images/I/413eOXUvr1L.jpg",
        "https://m.media-amazon.com/images/I/51NUWDrI-HL.jpg",
        "https://m.media-amazon.com/images/I/51j+IfgS8aL.jpg",
        "https://m.media-amazon.com/images/I/51Z-+aeEBML.jpg",
        "https://m.media-amazon.com/images/I/51nmdf7OUCL.jpg"
      ],
      "triggers": {
        "rating": 4.5,
        "reviews_count": 22675,
        "discount_percent": 5,
        "original_price": 19.85,
        "discount_amount": 0.99,
        "has_prime": true
      },
      "score": 7.0,
      "deal_number": 5,
      "deal_id": "#005"
    },
    {
      "asin": "B0G1XZHT7F",
      "url": "https://www.amazon.fr/dp/B0G1XZHT7F",
      "title_preview": "",
      "price_flash": "Prix Flash: 29,99 €",
      "original_price": "Le plus bas : 79,99 €",
      "discount_text": "",
      "category": "GPS et accessoires",
      "has_prime": false,
      "title": "Lot de 4 Traceur Tag Android & iOS, Compatible avec Apple Find My et Google Find Hub, Tracker GPS Android & iOS avec Batterie remplaçable, Traceur GPS Android pour Portefeuilles/Valises/Clés/Bagages",
      "price": 29.99,
      "price_original": 79.99,
      "images": [
        "https://m.media-amazon.com/images/I/71VNWKQ4dNL._AC_SL1500_.jpg",
        "https://m.media-amazon.com/images/I/41DHAiif++L.jpg",
        "https://m.media-amazon.com/images/I/41ptFpopxSL.jpg",
        "https://m.media-amazon.com/images/I/417JKvlvoTL.jpg",
        "https://m.media-amazon.com/images/I/41srHehr32L.jpg",
        "https://m.media-amazon.com/images/I/412gZSQBbeL.jpg",
        "https://m.media-amazon.com/images/I/41o+06a3EKL.jpg",
        "https://m.media-amazon.com/images/I/41clrCFwKnL.jpg"
      ],
      "triggers": {
        "rating": 4.6,
        "reviews_count": 172,
        "discount_percent": 63,
        "original_price": 79.99,
        "discount_amount": 50,
        "has_prime": true
      },
      "score": 6.5,
      "deal_number": 6,
      "deal_id": "#006"
    },
    {
      "asin": "B0CY1ZSQZ5",
      "url": "https://www.amazon.fr/dp/B0CY1ZSQZ5",
      "title_preview": "",
      "price_flash": "Prix Flash: 30,39 €",
      "original_price": "Le plus bas : 31,99 €",
      "discount_text": "",
      "category": "Bagages, sacs de voyage et accessoires",
      "has_prime": false,
      "title": "KLOSTAIN Sac à Dos Voyage Cabine Avion 45x36x20 pour Easyjet 30L Bagage Cabine Grande Bagage à Main sous Le Siège Sac à Dos Homme pour Ordinateur Portable 14 Noir",
      "price": 30.39,
      "price_original": 31.99,
      "images": [
        "https://m.media-amazon.com/images/I/81NCrngO16L._AC_SL1500_.jpg",
        "https://m.media-amazon.com/images/I/41eVXcSny9L.jpg",
        "https://m.media-amazon.com/images/I/511+uboryjL.jpg",
        "https://m.media-amazon.com/images/I/51Ggh9q2eWL.jpg",
        "https://m.media-amazon.com/images/I/51QyRa0gNiL.jpg",
        "https://m.media-amazon.com/images/I/51jGf3wrwgL.jpg",
        "https://m.media-amazon.com/images/I/412GrtlGEtL.jpg",
        "https://m.media-amazon.com/images/I/71bY-DPmn0L.SS40_BG85,85,85_BR-120_PKdp-play-icon-overlay__.jpg"
      ],
      "triggers": {
        "rating": 4.7,
        "reviews_count": 6799,
        "discount_percent": 5,
        "original_price": 31.99,
        "discount_amount": 1.6,
        "has_prime": true
      },
      "score": 6.0,
      "deal_number": 7,
      "deal_id": "#007"
    },
    {
      "asin": "B00MNBQ742",
      "url": "https://www.amazon.fr/dp/B00MNBQ742",
      "title_preview": "",
      "price_flash": "Prix Flash: 74,99 €",
      "original_price": "Le plus bas : 79,99 €",
      "discount_text": "",
      "category": "Petit électroménager",
      "has_prime": false,
      "title": "Moulinex Blender chauffant, 1000 W, Capacité 1.2 L, 5 programmes automatiques, Double paroi, Soupe, Velouté, Compote, Smoothie, Maintien au Chaud, Easy Soup silver LM841110",
      "price": 74.99,
      "price_original": 79.99,
      "images": [
        "https://m.media-amazon.com/images/I/71O84i1ENfL._AC_SL1500_.jpg",
        "https://m.media-amazon.com/images/I/41XzNkhFU2L.jpg",
        "https://m.media-amazon.com/images/I/512ZCgHWyIL.jpg",
        "https://m.media-amazon.com/images/I/31UyUaX+7dL.jpg",
        "https://m.media-amazon.com/images/I/510SFnA5ekL.jpg",
        "https://m.media-amazon.com/images/I/51Qdvuh+AoL.jpg",
        "https://m.media-amazon.com/images/I/41QcBCAuEiL.jpg"
      ],
      "triggers": {
        "rating": 4.5,
        "reviews_count": 6672,
        "discount_percent": 6,
        "original_price": 79.99,
        "discount_amount": 5,
        "has_prime": true
      },
      "score": 6.0,
      "deal_number": 8,
      "deal_id": "#008"
    },
    {
      "asin": "B0C9MBG966",
      "url": "https://www.amazon.fr/dp/B0C9MBG966",
      "title_preview": "",
      "price_flash": "Prix Flash: 52,99 €",
      "original_price": "Le plus bas : 62,90 €",
      "discount_text": "",
      "category": "Ameublement et décoration",
      "has_prime": false,
      "title": "Novilla Surmatelas 140 X 190 CM, Surmatelas en Mousse à Mémoire de Forme Gel, Épaisseur 5 CM, avec Design Antidérapant et Certification de Sécurité, sans Odeur, Housse Lavable",
      "price": 52.99,
      "price_original": 62.9,
      "images": [
        "https://m.media-amazon.com/images/I/61mgKAGSboL._AC_SL1500_.jpg",
        "https://m.media-amazon.com/images/I/31iln7wqGDL.jpg",
        "https://m.media-amazon.com/images/I/41nOOdPhJCL.jpg",
        "https://m.media-amazon.com/images/I/41O0d1MnAAL.jpg",
        "https://m.media-amazon.com/images/I/411KHqcmuaL.jpg",
        "https://m.media-amazon.com/images/I/41+3YkczE2L.jpg",
        "https://m.media-amazon.com/images/I/41cBwupnkpL.jpg"
      ],
      "triggers": {
        "rating": 4.5,
        "reviews_count": 1854,
        "discount_percent": 16,
        "original_price": 62.9,
        "discount_amount": 9.91,
        "has_prime": true
      },
      "score": 6.0,
      "deal_number": 9,
      "deal_id": "#009"
    },
    {
      "asin": "B0G2YVZMHQ",
      "url": "https://www.amazon.fr/dp/B0G2YVZMHQ",
      "title_preview": "",
      "price_flash": "Prix Flash: 110,99 €",
      "original_price": "Le plus bas : 116,99 €",
      "discount_text": "",
      "category": "Rangement et organisation",
      "has_prime": false,
      "title": "Leifheit Séchoir parapluie Linomatic 500 Deluxe, étendoir à linge avec rétractation automatique des fils, étendoir à linge extérieur avec 50m de fil, jusqu'à 5 machines à laver, douille de sol incluse",
      "price": 110.99,
      "price_original": 116.99,
      "images": [
        "https://m.media-amazon.com/images/I/51PVgcpg3wL._AC_SL1227_.jpg",
        "https://m.media-amazon.com/images/I/31sD5jl8fVL.jpg",
        "https://m.media-amazon.com/images/I/51B3ydjtOlL.jpg",
        "https://m.media-amazon.com/images/I/41DG-csglAL.jpg",
        "https://m.media-amazon.com/images/I/41BvUIwPqWL.jpg",
        "https://m.media-amazon.com/images/I/51hGWTjp+HL.jpg",
        "https://m.media-amazon.com/images/I/51YR4hN1quL.jpg"
      ],
      "triggers": {
        "rating": 4.5,
        "reviews_count": 7804,
        "discount_percent": 5,
        "original_price": 116.99,
        "discount_amount": 6,
        "has_prime": true
      },
      "score": 6.0,
      "deal_number": 10,
      "deal_id": "#010"
    },
    {
      "asin": "B0D5D55GXL",
      "url": "https://www.amazon.fr/dp/B0D5D55GXL",
      "title_preview": "",
      "price_flash": "Prix Flash: 215,00 €",
      "original_price": "Le plus bas : 269,99 €",
      "discount_text": "",
      "category": "Hygiène dentaire",
      "has_prime": false,
      "title": "Oral-B iO Série 9 Brosse à Dents Électrique Noire, Capteur De Pression, Modes Soin Des Gencives, Douceur Pour Protéger Des Dents Sensibles, 3 Têtes De Recharge, 1 Chargeur, 1 Étui De Voyage, En Carton",
      "price": 215,
      "price_original": 269.99,
      "images": [
        "https://m.media-amazon.com/images/I/611Z5K46KSL._AC_SL1100_.jpg",
        "https://m.media-amazon.com/images/I/41o8ZhOaxZL.jpg",
        "https://m.media-amazon.com/images/I/515u4bTmaTL.jpg",
        "https://m.media-amazon.com/images/I/51tGsXk4B+L.jpg",
        "https://m.media-amazon.com/images/I/41fLKSyCoWL.jpg",
        "https://m.media-amazon.com/images/I/51g5Atc18nL.jpg",
        "https://m.media-amazon.com/images/I/51qLDMWvTJL.jpg",
        "https://m.media-amazon.com/images/I/41UsLtGICbL.SS40_BG85,85,85_BR-120_PKdp-play-icon-overlay__.jpg"
      ],
      "triggers": {
        "rating": 4.6,
        "reviews_count": 197,
        "discount_percent": 20,
        "original_price": 269.99,
        "discount_amount": 54.99,
        "has_prime": true
      },
      "score": 5.0,
      "deal_number": 11,
      "deal_id": "#011"
    },
    {
      "asin": "B0FY2NRCYR",
      "url": "https://www.amazon.fr/dp/B0FY2NRCYR",
      "title_preview": "",
      "price_flash": "Prix Flash: 65,87 €",
      "original_price": "Le plus bas : 69,34 €",
      "discount_text": "",
      "category": "Écrans PC",
      "has_prime": false,
      "title": "Ingnok Écran Portable 15,6\", FHD 1080P IPS Moniteur Portable avec Haut-parleurs Intégré, Ultra-Leger Ecran Portatif pour Ordinateur Portable/PC/Mac/PS3/4/5/X-box - Connectivité USB C et HDMI",
      "price": 65.87,
      "price_original": 69.34,
      "images": [
        "https://m.media-amazon.com/images/I/71PYfOBmAkL._AC_SL1500_.jpg",
        "https://m.media-amazon.com/images/I/41rtVrh0lIL.jpg",
        "https://m.media-amazon.com/images/I/51PnxKNNv6L.jpg",
        "https://m.media-amazon.com/images/I/51KccidT0LL.jpg",
        "https://m.media-amazon.com/images/I/41F-HrlLXlL.jpg",
        "https://m.media-amazon.com/images/I/519Zs4HFk-L.jpg",
        "https://m.media-amazon.com/images/I/51LZerfnaML.jpg",
        "https://m.media-amazon.com/images/I/519fbklBgrL.SS40_BG85,85,85_BR-120_PKdp-play-icon-overlay__.jpg"
      ],
      "triggers": {
        "rating": 4.5,
        "reviews_count": 3623,
        "discount_percent": 5,
        "original_price": 69.34,
        "discount_amount": 3.47,
        "has_prime": true
      },
      "score": 5.0,
      "deal_number": 12,
      "deal_id": "#012"
    },
    {
      "asin": "B0F3P4G6CK",
      "url": "https://www.amazon.fr/dp/B0F3P4G6CK",
      "title_preview": "",
      "price_flash": "Prix Flash: 19,50 €",
      "original_price": "Le plus bas : 22,48 €",
      "discount_text": "",
      "category": "Entretien de la maison et nettoyage",
      "has_prime": false,
      "title": "Lenor Adoucissant Lenor 216 Lavages (27x8), Parfum Envolée d’Air, 24H De Fraîcheur Relaxante, Avec Une Touche D’Huiles Essentielles, Testé Dermatologiquement, Fabriqué En France",
      "price": 19.5,
      "price_original": 22.48,
      "images": [
        "https://m.media-amazon.com/images/I/81rEr-01HmL._AC_SL1500_.jpg",
        "https://m.media-amazon.com/images/I/5181y9qBvRL.jpg",
        "https://m.media-amazon.com/images/I/51O7PUkJq+L.jpg",
        "https://m.media-amazon.com/images/I/51SDV2NIihL.jpg",
        "https://m.media-amazon.com/images/I/51voZI2yBEL.jpg",
        "https://m.media-amazon.com/images/I/41WcCEjy4YL.jpg",
        "https://m.media-amazon.com/images/I/51soO7UVf6L.jpg",
        "https://m.media-amazon.com/images/I/51wAn0vKl7L.jpg"
      ],
      "triggers": {
        "rating": 4.6,
        "reviews_count": 427,
        "discount_percent": 13,
        "original_price": 22.48,
        "discount_amount": 2.98,
        "has_prime": true
      },
      "score": 5.0,
      "deal_number": 13,
      "deal_id": "#013"
    },
    {
      "asin": "B0F99N77VY",
      "url": "https://www.amazon.fr/dp/B0F99N77VY",
      "title_preview": "",
      "price_flash": "Prix Flash: 21,84 €",
      "original_price": "Le plus bas : 22,99 €",
      "discount_text": "",
      "category": "Electronique embarquée",
      "has_prime": false,
      "title": "S2 Mini Adaptateur CarPlay sans Fil pour iPhone, Convertissez Le Filaire en sans Fil, Plug & Play avec Typ-C/USB, Compatible avec Les Voitures à partir de 2016 et iOS 10+ (Noir)",
      "price": 21.84,
      "price_original": 22.99,
      "images": [
        "https://m.media-amazon.com/images/I/61VazYvuDAL._AC_SL1500_.jpg",
        "https://m.media-amazon.com/images/I/31iQEXODRTL.jpg",
        "https://m.media-amazon.com/images/I/41UWD3gNFdL.jpg",
        "https://m.media-amazon.com/images/I/41De+LJ-H+L.jpg",
        "https://m.media-amazon.com/images/I/41F6-AlN8HL.jpg",
        "https://m.media-amazon.com/images/I/512dilGsXUL.jpg",
        "https://m.media-amazon.com/images/I/41irEreFSvL.jpg",
        "https://m.media-amazon.com/images/I/71Tsxw+mRFL.SS40_BG85,85,85_BR-120_PKdp-play-icon-overlay__.jpg"
      ],
      "triggers": {
        "rating": 4.1,
        "reviews_count": 1131,
        "discount_percent": 5,
        "original_price": 22.99,
        "discount_amount": 1.15,
        "has_prime": true
      },
      "score": 4.5,
      "deal_number": 14,
      "deal_id": "#014"
    },
    {
      "asin": "B0D2L5YFBG",
      "url": "https://www.amazon.fr/dp/B0D2L5YFBG",
      "title_preview": "",
      "price_flash": "Prix Flash: 63,48 €",
      "original_price": "Le plus bas : 74,99 €",
      "discount_text": "",
      "category": "Écrans PC",
      "has_prime": false,
      "title": "Ecran Portable 15.6 Pouces, Moniteur Portable 1080P FHD IPS, Écran Portatif avec Mini HDMI USB C, pour Laptop, PC, PS5, Xbox",
      "price": 63.48,
      "price_original": 74.99,
      "images": [
        "https://m.media-amazon.com/images/I/71MxrgXdo-L._AC_SL1500_.jpg",
        "https://m.media-amazon.com/images/I/51EbFEnVSnL.jpg",
        "https://m.media-amazon.com/images/I/51lOCGsAkNL.jpg",
        "https://m.media-amazon.com/images/I/518FiRE-6NL.jpg",
        "https://m.media-amazon.com/images/I/417xrLnSY0L.jpg",
        "https://m.media-amazon.com/images/I/51P49WbLwtL.jpg",
        "https://m.media-amazon.com/images/I/51cSD+-snGL.jpg",
        "https://m.media-amazon.com/images/I/51KA9DNZrLL.SS40_BG85,85,85_BR-120_PKdp-play-icon-overlay__.jpg"
      ],
      "triggers": {
        "rating": 4.4,
        "reviews_count": 464,
        "discount_percent": 15,
        "original_price": 74.99,
        "discount_amount": 11.51,
        "has_prime": true
      },
      "score": 4.5,
      "deal_number": 15,
      "deal_id": "#015"
    },
    {
      "asin": "B0DPQ6QFWL",
      "url": "https://www.amazon.fr/dp/B0DPQ6QFWL",
      "title_preview": "",
      "price_flash": "Prix Flash: 47,49 €",
      "original_price": "Le plus bas : 49,99 €",
      "discount_text": "",
      "category": "Technologie portable",
      "has_prime": false,
      "title": "Montre Connectée Femme pour Samsung, iPhone, Android, 1.8\" Smartwatch avec Appel Bluetooth, Voix de l'IA, Alexa intégrée, Smartwatch Moniteur, Calories, IP68 Montre Intelligente, Podometre",
      "price": 47.49,
      "price_original": 49.99,
      "images": [
        "https://m.media-amazon.com/images/I/71GT31RwkgL._AC_SL1500_.jpg",
        "https://m.media-amazon.com/images/I/41Mucu1LeqL.jpg",
        "https://m.media-amazon.com/images/I/51CiwCq83+L.jpg",
        "https://m.media-amazon.com/images/I/41ml8LdOr3L.jpg",
        "https://m.media-amazon.com/images/I/41buQmq7fxL.jpg",
        "https://m.media-amazon.com/images/I/51vnl8ipodL.jpg",
        "https://m.media-amazon.com/images/I/415XZTXn8xL.jpg"
      ],
      "triggers": {
        "rating": 4.4,
        "reviews_count": 1480,
        "discount_percent": 5,
        "original_price": 49.99,
        "discount_amount": 2.5,
        "has_prime": true
      },
      "score": 4.5,
      "deal_number": 16,
      "deal_id": "#016"
    },
    {
      "asin": "B0CZMT61F7",
      "url": "https://www.amazon.fr/dp/B0CZMT61F7",
      "title_preview": "",
      "price_flash": "Prix Flash: 32,48 €",
      "original_price": "Le plus bas : 34,19 €",
      "discount_text": "",
      "category": "Petites fournitures",
      "has_prime": false,
      "title": "Souffleur Air Comprimé, 100000 TR/Min de Souffleur pc avec Batterie 9000mAh, Bombe Air Sec - Nettoyage PC, Plumeau Air Comprimé à 3 Vitessesavec Lumière LED pour Le Nettoyage de Canapé, Voiture",
      "price": 32.48,
      "price_original": 34.19,
      "images": [
        "https://m.media-amazon.com/images/I/71RF7SzJ-lL._AC_SL1500_.jpg",
        "https://m.media-amazon.com/images/I/51aMpoNfvbL.jpg",
        "https://m.media-amazon.com/images/I/41YnlZmbbyL.jpg",
        "https://m.media-amazon.com/images/I/51XwJNZncGL.jpg",
        "https://m.media-amazon.com/images/I/5150vgMKN9L.jpg",
        "https://m.media-amazon.com/images/I/51NyDna3mcL.jpg",
        "https://m.media-amazon.com/images/I/41WgLcU5NiL.jpg",
        "https://m.media-amazon.com/images/I/51bUHQ9UYHL.jpg"
      ],
      "triggers": {
        "rating": 4.3,
        "reviews_count": 1483,
        "discount_percent": 5,
        "original_price": 34.19,
        "discount_amount": 1.71,
        "has_prime": true
      },
      "score": 4.5,
      "deal_number": 17,
      "deal_id": "#017"
    },
    {
      "asin": "B0G1XFDP75",
      "url": "https://www.amazon.fr/dp/B0G1XFDP75",
      "title_preview": "",
      "price_flash": "Prix Flash: 179,99 €",
      "original_price": "Le plus bas : 189,99 €",
      "discount_text": "",
      "category": "Aspirateurs, entretien des sols et nettoyeurs de vitres",
      "has_prime": false,
      "title": "SunSare Aspirateur Balai sans Fil, 600W/50KPA/65Mins Aspirateur sans Fil Puissant avec Pliable Adaptateur, Tuyau 1M, Parfumé, Chargement Mural, Aspirateur Balai pour Poils d’Animaux/Sols/Tapis",
      "price": 179.99,
      "price_original": 189.99,
      "images": [
        "https://m.media-amazon.com/images/I/71qeciA31bL._AC_SL1500_.jpg",
        "https://m.media-amazon.com/images/I/41zsGfuydwL.jpg",
        "https://m.media-amazon.com/images/I/51vXTsRKa8L.jpg",
        "https://m.media-amazon.com/images/I/41Y-PryVwCL.jpg",
        "https://m.media-amazon.com/images/I/41oSC4IEcgL.jpg",
        "https://m.media-amazon.com/images/I/41ya+f0n03L.jpg",
        "https://m.media-amazon.com/images/I/51+bxBsse8L.jpg"
      ],
      "triggers": {
        "rating": 4.8,
        "reviews_count": 290,
        "discount_percent": 5,
        "original_price": 189.99,
        "discount_amount": 10,
        "has_prime": true
      },
      "score": 4.0,
      "deal_number": 18,
      "deal_id": "#018"
    },
    {
      "asin": "B0DT493J7J",
      "url": "https://www.amazon.fr/dp/B0DT493J7J",
      "title_preview": "",
      "price_flash": "Prix Flash: 56,90 €",
      "original_price": "Le plus bas : 61,66 €",
      "discount_text": "",
      "category": "Rasage et épilation",
      "has_prime": false,
      "title": "Gillette Lot De 20 Recharges De Rasoir Pour Hommes Proglide, AUTHENTIQUES, Cartouche A 5 Lames Ultra-Affutées, Nouvelle Lubrification, Bande Lubrifiante x2, Rasage Du Visage Flexible",
      "price": 56.9,
      "price_original": 61.66,
      "images": [
        "https://m.media-amazon.com/images/I/71z3LW5SjOL._AC_SL1500_.jpg",
        "https://m.media-amazon.com/images/I/41ZDH7CHNyL.jpg",
        "https://m.media-amazon.com/images/I/41etcejAa4L.jpg",
        "https://m.media-amazon.com/images/I/511SvYkf0TL.jpg",
        "https://m.media-amazon.com/images/I/41kPY1-sc3L.jpg",
        "https://m.media-amazon.com/images/I/51qrx3-0q2L.jpg",
        "https://m.media-amazon.com/images/I/41djUQhlFTL.jpg",
        "https://m.media-amazon.com/images/I/51owtod6IYL.jpg"
      ],
      "triggers": {
        "rating": 4.6,
        "reviews_count": 871,
        "discount_percent": 8,
        "original_price": 61.66,
        "discount_amount": 4.76,
        "has_prime": true
      },
      "score": 4.0,
      "deal_number": 19,
      "deal_id": "#019"
    },
    {
      "asin": "B08BQXK62C",
      "url": "https://www.amazon.fr/dp/B08BQXK62C",
      "title_preview": "",
      "price_flash": "Prix Flash: 679,79 €",
      "original_price": "Le plus bas : 759,90 €",
      "discount_text": "",
      "category": "Mobilier de jardin",
      "has_prime": false,
      "title": "tectake® Ensemble de 4 Fauteuils Confortables avec Accoudoirs, Salon de Jardin Exterieur ou Intérieur, PolyRotin et Aluminium, Coussins Inclus, Mobilier de Jardin Amenagement Balcon Terrasse Veranda",
      "price": 679.79,
      "price_original": 759.9,
      "images": [
        "https://m.media-amazon.com/images/I/81jOjDCPwsL._AC_SL1350_.jpg",
        "https://m.media-amazon.com/images/I/51T7WOLKF6L.jpg",
        "https://m.media-amazon.com/images/I/51KoALCFQFL.jpg",
        "https://m.media-amazon.com/images/I/41ODoSeYvlL.jpg",
        "https://m.media-amazon.com/images/I/51EbkvXdwdL.jpg",
        "https://m.media-amazon.com/images/I/41trrPEXBDL.jpg",
        "https://m.media-amazon.com/images/I/51POCSS7w6L.jpg",
        "https://m.media-amazon.com/images/I/51ipY7b8J4L.jpg"
      ],
      "triggers": {
        "rating": 4.4,
        "reviews_count": 147,
        "discount_percent": 11,
        "original_price": 759.9,
        "discount_amount": 80.11,
        "has_prime": true
      },
      "score": 4.0,
      "deal_number": 20,
      "deal_id": "#020"
    }
  ],
  "by_category": {
    "Aspirateurs, entretien des sols et nettoyeurs de vitres": [
      {
        "asin": "B0FSL2L7LW",
        "url": "https://www.amazon.fr/dp/B0FSL2L7LW",
        "title_preview": "",
        "price_flash": "Prix Flash: 299,98 €",
        "original_price": "Le plus bas : 999,99 €",
        "discount_text": "",
        "category": "Aspirateurs, entretien des sols et nettoyeurs de vitres",
        "has_prime": false,
        "title": "Lefant M3 Robot Aspirateur Laveur 12 000 Pa, Station Multifonctionnelle, Double Serpillière Rotative 200 TR/Min, Navigation dToF, Évitement d'obstacles PSD, 220min, 30 réglages de Niveau d'eau",
        "price": 299.98,
        "price_original": 999.99,
        "images": [
          "https://m.media-amazon.com/images/I/71i35ufWOXL._AC_SL1500_.jpg",
          "https://m.media-amazon.com/images/I/41q7yOd0YyL.jpg",
          "https://m.media-amazon.com/images/I/41G9RD2oc4L.jpg",
          "https://m.media-amazon.com/images/I/41Q2igEWjpL.jpg",
          "https://m.media-amazon.com/images/I/416l028hncL.jpg",
          "https://m.media-amazon.com/images/I/51wIsstigzL.jpg",
          "https://m.media-amazon.com/images/I/51H2s-fJbPL.jpg",
          "https://m.media-amazon.com/images/I/41i7pvoAzQL.jpg"
        ],
        "triggers": {
          "rating": 4.3,
          "reviews_count": 2607,
          "discount_percent": 70,
          "original_price": 999.99,
          "discount_amount": 700.01,
          "has_prime": true
        },
        "score": 7.5,
        "deal_number": 1,
        "deal_id": "#001"
      },
      {
        "asin": "B0G1XFDP75",
        "url": "https://www.amazon.fr/dp/B0G1XFDP75",
        "title_preview": "",
        "price_flash": "Prix Flash: 179,99 €",
        "original_price": "Le plus bas : 189,99 €",
        "discount_text": "",
        "category": "Aspirateurs, entretien des sols et nettoyeurs de vitres",
        "has_prime": false,
        "title": "SunSare Aspirateur Balai sans Fil, 600W/50KPA/65Mins Aspirateur sans Fil Puissant avec Pliable Adaptateur, Tuyau 1M, Parfumé, Chargement Mural, Aspirateur Balai pour Poils d’Animaux/Sols/Tapis",
        "price": 179.99,
        "price_original": 189.99,
        "images": [
          "https://m.media-amazon.com/images/I/71qeciA31bL._AC_SL1500_.jpg",
          "https://m.media-amazon.com/images/I/41zsGfuydwL.jpg",
          "https://m.media-amazon.com/images/I/51vXTsRKa8L.jpg",
          "https://m.media-amazon.com/images/I/41Y-PryVwCL.jpg",
          "https://m.media-amazon.com/images/I/41oSC4IEcgL.jpg",
          "https://m.media-amazon.com/images/I/41ya+f0n03L.jpg",
          "https://m.media-amazon.com/images/I/51+bxBsse8L.jpg"
        ],
        "triggers": {
          "rating": 4.8,
          "reviews_count": 290,
          "discount_percent": 5,
          "original_price": 189.99,
          "discount_amount": 10,
          "has_prime": true
        },
        "score": 4.0,
        "deal_number": 18,
        "deal_id": "#018"
      }
    ],
    "Vitamines, minéraux et compléments": [
      {
        "asin": "B091GB1NP1",
        "url": "https://www.amazon.fr/dp/B091GB1NP1",
        "title_preview": "",
        "price_flash": "Prix Flash: 18,99 €",
        "original_price": "Le plus bas : 22,99 €",
        "discount_text": "",
        "category": "Vitamines, minéraux et compléments",
        "has_prime": false,
        "title": "Vitamine D3 K2 MK7, 365 Micro-Comprimés Végétariens (pour 1 An), Combinaison Vit D3 2000UI Cholécalciférol avec Vitamine K2 MK7 200μg Ménaquinone, sans Stéarate de Magnésium",
        "price": 18.99,
        "price_original": 22.99,
        "images": [
          "https://m.media-amazon.com/images/I/71dQNhLYgeL._AC_SL1500_.jpg",
          "https://m.media-amazon.com/images/I/41AdssjR5pL.jpg",
          "https://m.media-amazon.com/images/I/41lFe6LTfQL.jpg",
          "https://m.media-amazon.com/images/I/41+nkFa3CyL.jpg",
          "https://m.media-amazon.com/images/I/516H24Q0E8L.jpg",
          "https://m.media-amazon.com/images/I/51NPKIixE8L.jpg",
          "https://m.media-amazon.com/images/I/41OSJW1YJHL.jpg",
          "https://m.media-amazon.com/images/I/31pl4d8ydVL.jpg"
        ],
        "triggers": {
          "rating": 4.5,
          "reviews_count": 6417,
          "discount_percent": 17,
          "original_price": 22.99,
          "discount_amount": 4,
          "has_prime": true
        },
        "score": 7.0,
        "deal_number": 2,
        "deal_id": "#002"
      }
    ],
    "Ameublement et décoration": [
      {
        "asin": "B075JMFTB8",
        "url": "https://www.amazon.fr/dp/B075JMFTB8",
        "title_preview": "",
        "price_flash": "Prix Flash: 26,50 €",
        "original_price": "Le plus bas : 27,90 €",
        "discount_text": "",
        "category": "Ameublement et décoration",
        "has_prime": false,
        "title": "Utopia Bedding Couette 220x240 cm, Couette Chaud 370 GSM, pour lit 2 Personne, Couverture Blanc avec Onglets d'angle (Blanc)",
        "price": 26.5,
        "price_original": 27.9,
        "images": [
          "https://m.media-amazon.com/images/I/81MuXSwe-ZL._AC_SL1500_.jpg",
          "https://m.media-amazon.com/images/I/51i7V-2KJ7L.jpg",
          "https://m.media-amazon.com/images/I/31NP3zWi+QL.jpg",
          "https://m.media-amazon.com/images/I/41f5igACPML.jpg",
          "https://m.media-amazon.com/images/I/31Prnrf+rVL.jpg"
        ],
        "triggers": {
          "rating": 4.5,
          "reviews_count": 39434,
          "discount_percent": 5,
          "original_price": 27.9,
          "discount_amount": 1.4,
          "has_prime": true
        },
        "score": 7.0,
        "deal_number": 3,
        "deal_id": "#003"
      },
      {
        "asin": "B07CB94N28",
        "url": "https://www.amazon.fr/dp/B07CB94N28",
        "title_preview": "",
        "price_flash": "Prix Flash: 11,99 €",
        "original_price": "Le plus bas : 12,62 €",
        "discount_text": "",
        "category": "Ameublement et décoration",
        "has_prime": false,
        "title": "Utopia Bedding Drap Housse - Gris, 160 x 200 cm - Coupes de 35 cm pour Matelas épais - Polyester Microfibre brossée",
        "price": 11.99,
        "price_original": 12.62,
        "images": [
          "https://m.media-amazon.com/images/I/71k1qAeLoAL._AC_SL1500_.jpg",
          "https://m.media-amazon.com/images/I/41w1GUR+66L.jpg",
          "https://m.media-amazon.com/images/I/41FM-SawD0L.jpg",
          "https://m.media-amazon.com/images/I/41DuaiF+lZL.jpg",
          "https://m.media-amazon.com/images/I/41LfnP4PThL.jpg",
          "https://m.media-amazon.com/images/I/51+SnG-KPOL.jpg",
          "https://m.media-amazon.com/images/I/41FSLnmYy9L.jpg"
        ],
        "triggers": {
          "rating": 4.6,
          "reviews_count": 161412,
          "discount_percent": 5,
          "original_price": 12.62,
          "discount_amount": 0.63,
          "has_prime": true
        },
        "score": 7.0,
        "deal_number": 4,
        "deal_id": "#004"
      },
      {
        "asin": "B0CYPY3G8B",
        "url": "https://www.amazon.fr/dp/B0CYPY3G8B",
        "title_preview": "",
        "price_flash": "Prix Flash: 18,86 €",
        "original_price": "Le plus bas : 19,85 €",
        "discount_text": "",
        "category": "Ameublement et décoration",
        "has_prime": false,
        "title": "Utopia Bedding Housse De Matelas 140 x 190 x 20 cm Imperméable Avec Fermeture éclair, Certifié Oeko-TEX, Protégé Matelas, Blanc",
        "price": 18.86,
        "price_original": 19.85,
        "images": [
          "https://m.media-amazon.com/images/I/71-sHDrPc0L._AC_SL1500_.jpg",
          "https://m.media-amazon.com/images/I/41xQPZwIqQL.jpg",
          "https://m.media-amazon.com/images/I/413eOXUvr1L.jpg",
          "https://m.media-amazon.com/images/I/51NUWDrI-HL.jpg",
          "https://m.media-amazon.com/images/I/51j+IfgS8aL.jpg",
          "https://m.media-amazon.com/images/I/51Z-+aeEBML.jpg",
          "https://m.media-amazon.com/images/I/51nmdf7OUCL.jpg"
        ],
        "triggers": {
          "rating": 4.5,
          "reviews_count": 22675,
          "discount_percent": 5,
          "original_price": 19.85,
          "discount_amount": 0.99,
          "has_prime": true
        },
        "score": 7.0,
        "deal_number": 5,
        "deal_id": "#005"
      },
      {
        "asin": "B0C9MBG966",
        "url": "https://www.amazon.fr/dp/B0C9MBG966",
        "title_preview": "",
        "price_flash": "Prix Flash: 52,99 €",
        "original_price": "Le plus bas : 62,90 €",
        "discount_text": "",
        "category": "Ameublement et décoration",
        "has_prime": false,
        "title": "Novilla Surmatelas 140 X 190 CM, Surmatelas en Mousse à Mémoire de Forme Gel, Épaisseur 5 CM, avec Design Antidérapant et Certification de Sécurité, sans Odeur, Housse Lavable",
        "price": 52.99,
        "price_original": 62.9,
        "images": [
          "https://m.media-amazon.com/images/I/61mgKAGSboL._AC_SL1500_.jpg",
          "https://m.media-amazon.com/images/I/31iln7wqGDL.jpg",
          "https://m.media-amazon.com/images/I/41nOOdPhJCL.jpg",
          "https://m.media-amazon.com/images/I/41O0d1MnAAL.jpg",
          "https://m.media-amazon.com/images/I/411KHqcmuaL.jpg",
          "https://m.media-amazon.com/images/I/41+3YkczE2L.jpg",
          "https://m.media-amazon.com/images/I/41cBwupnkpL.jpg"
        ],
        "triggers": {
          "rating": 4.5,
          "reviews_count": 1854,
          "discount_percent": 16,
          "original_price": 62.9,
          "discount_amount": 9.91,
          "has_prime": true
        },
        "score": 6.0,
        "deal_number": 9,
        "deal_id": "#009"
      },
      {
        "asin": "B0D5PR4VJ5",
        "url": "https://www.amazon.fr/dp/B0D5PR4VJ5",
        "title_preview": "",
        "price_flash": "Prix Flash: 75,99 €",
        "original_price": "Le plus bas : 79,99 €",
        "discount_text": "",
        "category": "Ameublement et décoration",
        "has_prime": false,
        "title": "EUGAD Lot de 2 Tabourets de Cuisine Haut, Tabouret de Bar Rond à Hauteur Réglable, Pivotant, avec Repose-Pieds, Siège Rembourré en Similucuir Vintage, Marron, 1085BY-2",
        "price": 75.99,
        "price_original": 79.99,
        "images": [
          "https://m.media-amazon.com/images/I/61YfElBIwgL._AC_SL1500_.jpg",
          "https://m.media-amazon.com/images/I/41mDZMQ5fNL.jpg",
          "https://m.media-amazon.com/images/I/51XAB8QBCFL.jpg",
          "https://m.media-amazon.com/images/I/41gVomE6RBL.jpg",
          "https://m.media-amazon.com/images/I/41227VO3HmL.jpg",
          "https://m.media-amazon.com/images/I/41knBLZOLVL.jpg",
          "https://m.media-amazon.com/images/I/51iqWsjSG-L.jpg",
          "https://m.media-amazon.com/images/I/51jbPA7rCnL.jpg"
        ],
        "triggers": {
          "rating": 4.6,
          "reviews_count": 96,
          "discount_percent": 5,
          "original_price": 79.99,
          "discount_amount": 4,
          "has_prime": true
        },
        "score": 3.5,
        "deal_number": 24,
        "deal_id": "#024"
      }
    ],
    "GPS et accessoires": [
      {
        "asin": "B0G1XZHT7F",
        "url": "https://www.amazon.fr/dp/B0G1XZHT7F",
        "title_preview": "",
        "price_flash": "Prix Flash: 29,99 €",
        "original_price": "Le plus bas : 79,99 €",
        "discount_text": "",
        "category": "GPS et accessoires",
        "has_prime": false,
        "title": "Lot de 4 Traceur Tag Android & iOS, Compatible avec Apple Find My et Google Find Hub, Tracker GPS Android & iOS avec Batterie remplaçable, Traceur GPS Android pour Portefeuilles/Valises/Clés/Bagages",
        "price": 29.99,
        "price_original": 79.99,
        "images": [
          "https://m.media-amazon.com/images/I/71VNWKQ4dNL._AC_SL1500_.jpg",
          "https://m.media-amazon.com/images/I/41DHAiif++L.jpg",
          "https://m.media-amazon.com/images/I/41ptFpopxSL.jpg",
          "https://m.media-amazon.com/images/I/417JKvlvoTL.jpg",
          "https://m.media-amazon.com/images/I/41srHehr32L.jpg",
          "https://m.media-amazon.com/images/I/412gZSQBbeL.jpg",
          "https://m.media-amazon.com/images/I/41o+06a3EKL.jpg",
          "https://m.media-amazon.com/images/I/41clrCFwKnL.jpg"
        ],
        "triggers": {
          "rating": 4.6,
          "reviews_count": 172,
          "discount_percent": 63,
          "original_price": 79.99,
          "discount_amount": 50,
          "has_prime": true
        },
        "score": 6.5,
        "deal_number": 6,
        "deal_id": "#006"
      }
    ],
    "Bagages, sacs de voyage et accessoires": [
      {
        "asin": "B0CY1ZSQZ5",
        "url": "https://www.amazon.fr/dp/B0CY1ZSQZ5",
        "title_preview": "",
        "price_flash": "Prix Flash: 30,39 €",
        "original_price": "Le plus bas : 31,99 €",
        "discount_text": "",
        "category": "Bagages, sacs de voyage et accessoires",
        "has_prime": false,
        "title": "KLOSTAIN Sac à Dos Voyage Cabine Avion 45x36x20 pour Easyjet 30L Bagage Cabine Grande Bagage à Main sous Le Siège Sac à Dos Homme pour Ordinateur Portable 14 Noir",
        "price": 30.39,
        "price_original": 31.99,
        "images": [
          "https://m.media-amazon.com/images/I/81NCrngO16L._AC_SL1500_.jpg",
          "https://m.media-amazon.com/images/I/41eVXcSny9L.jpg",
          "https://m.media-amazon.com/images/I/511+uboryjL.jpg",
          "https://m.media-amazon.com/images/I/51Ggh9q2eWL.jpg",
          "https://m.media-amazon.com/images/I/51QyRa0gNiL.jpg",
          "https://m.media-amazon.com/images/I/51jGf3wrwgL.jpg",
          "https://m.media-amazon.com/images/I/412GrtlGEtL.jpg",
          "https://m.media-amazon.com/images/I/71bY-DPmn0L.SS40_BG85,85,85_BR-120_PKdp-play-icon-overlay__.jpg"
        ],
        "triggers": {
          "rating": 4.7,
          "reviews_count": 6799,
          "discount_percent": 5,
          "original_price": 31.99,
          "discount_amount": 1.6,
          "has_prime": true
        },
        "score": 6.0,
        "deal_number": 7,
        "deal_id": "#007"
      }
    ],
    "Petit électroménager": [
      {
        "asin": "B00MNBQ742",
        "url": "https://www.amazon.fr/dp/B00MNBQ742",
        "title_preview": "",
        "price_flash": "Prix Flash: 74,99 €",
        "original_price": "Le plus bas : 79,99 €",
        "discount_text": "",
        "category": "Petit électroménager",
        "has_prime": false,
        "title": "Moulinex Blender chauffant, 1000 W, Capacité 1.2 L, 5 programmes automatiques, Double paroi, Soupe, Velouté, Compote, Smoothie, Maintien au Chaud, Easy Soup silver LM841110",
        "price": 74.99,
        "price_original": 79.99,
        "images": [
          "https://m.media-amazon.com/images/I/71O84i1ENfL._AC_SL1500_.jpg",
          "https://m.media-amazon.com/images/I/41XzNkhFU2L.jpg",
          "https://m.media-amazon.com/images/I/512ZCgHWyIL.jpg",
          "https://m.media-amazon.com/images/I/31UyUaX+7dL.jpg",
          "https://m.media-amazon.com/images/I/510SFnA5ekL.jpg",
          "https://m.media-amazon.com/images/I/51Qdvuh+AoL.jpg",
          "https://m.media-amazon.com/images/I/41QcBCAuEiL.jpg"
        ],
        "triggers": {
          "rating": 4.5,
          "reviews_count": 6672,
          "discount_percent": 6,
          "original_price": 79.99,
          "discount_amount": 5,
          "has_prime": true
        },
        "score": 6.0,
        "deal_number": 8,
        "deal_id": "#008"
      }
    ],
    "Rangement et organisation": [
      {
        "asin": "B0G2YVZMHQ",
        "url": "https://www.amazon.fr/dp/B0G2YVZMHQ",
        "title_preview": "",
        "price_flash": "Prix Flash: 110,99 €",
        "original_price": "Le plus bas : 116,99 €",
        "discount_text": "",
        "category": "Rangement et organisation",
        "has_prime": false,
        "title": "Leifheit Séchoir parapluie Linomatic 500 Deluxe, étendoir à linge avec rétractation automatique des fils, étendoir à linge extérieur avec 50m de fil, jusqu'à 5 machines à laver, douille de sol incluse",
        "price": 110.99,
        "price_original": 116.99,
        "images": [
          "https://m.media-amazon.com/images/I/51PVgcpg3wL._AC_SL1227_.jpg",
          "https://m.media-amazon.com/images/I/31sD5jl8fVL.jpg",
          "https://m.media-amazon.com/images/I/51B3ydjtOlL.jpg",
          "https://m.media-amazon.com/images/I/41DG-csglAL.jpg",
          "https://m.media-amazon.com/images/I/41BvUIwPqWL.jpg",
          "https://m.media-amazon.com/images/I/51hGWTjp+HL.jpg",
          "https://m.media-amazon.com/images/I/51YR4hN1quL.jpg"
        ],
        "triggers": {
          "rating": 4.5,
          "reviews_count": 7804,
          "discount_percent": 5,
          "original_price": 116.99,
          "discount_amount": 6,
          "has_prime": true
        },
        "score": 6.0,
        "deal_number": 10,
        "deal_id": "#010"
      }
    ],
    "Hygiène dentaire": [
      {
        "asin": "B0D5D55GXL",
        "url": "https://www.amazon.fr/dp/B0D5D55GXL",
        "title_preview": "",
        "price_flash": "Prix Flash: 215,00 €",
        "original_price": "Le plus bas : 269,99 €",
        "discount_text": "",
        "category": "Hygiène dentaire",
        "has_prime": false,
        "title": "Oral-B iO Série 9 Brosse à Dents Électrique Noire, Capteur De Pression, Modes Soin Des Gencives, Douceur Pour Protéger Des Dents Sensibles, 3 Têtes De Recharge, 1 Chargeur, 1 Étui De Voyage, En Carton",
        "price": 215,
        "price_original": 269.99,
        "images": [
          "https://m.media-amazon.com/images/I/611Z5K46KSL._AC_SL1100_.jpg",
          "https://m.media-amazon.com/images/I/41o8ZhOaxZL.jpg",
          "https://m.media-amazon.com/images/I/515u4bTmaTL.jpg",
          "https://m.media-amazon.com/images/I/51tGsXk4B+L.jpg",
          "https://m.media-amazon.com/images/I/41fLKSyCoWL.jpg",
          "https://m.media-amazon.com/images/I/51g5Atc18nL.jpg",
          "https://m.media-amazon.com/images/I/51qLDMWvTJL.jpg",
          "https://m.media-amazon.com/images/I/41UsLtGICbL.SS40_BG85,85,85_BR-120_PKdp-play-icon-overlay__.jpg"
        ],
        "triggers": {
          "rating": 4.6,
          "reviews_count": 197,
          "discount_percent": 20,
          "original_price": 269.99,
          "discount_amount": 54.99,
          "has_prime": true
        },
        "score": 5.0,
        "deal_number": 11,
        "deal_id": "#011"
      }
    ],
    "Écrans PC": [
      {
        "asin": "B0FY2NRCYR",
        "url": "https://www.amazon.fr/dp/B0FY2NRCYR",
        "title_preview": "",
        "price_flash": "Prix Flash: 65,87 €",
        "original_price": "Le plus bas : 69,34 €",
        "discount_text": "",
        "category": "Écrans PC",
        "has_prime": false,
        "title": "Ingnok Écran Portable 15,6\", FHD 1080P IPS Moniteur Portable avec Haut-parleurs Intégré, Ultra-Leger Ecran Portatif pour Ordinateur Portable/PC/Mac/PS3/4/5/X-box - Connectivité USB C et HDMI",
        "price": 65.87,
        "price_original": 69.34,
        "images": [
          "https://m.media-amazon.com/images/I/71PYfOBmAkL._AC_SL1500_.jpg",
          "https://m.media-amazon.com/images/I/41rtVrh0lIL.jpg",
          "https://m.media-amazon.com/images/I/51PnxKNNv6L.jpg",
          "https://m.media-amazon.com/images/I/51KccidT0LL.jpg",
          "https://m.media-amazon.com/images/I/41F-HrlLXlL.jpg",
          "https://m.media-amazon.com/images/I/519Zs4HFk-L.jpg",
          "https://m.media-amazon.com/images/I/51LZerfnaML.jpg",
          "https://m.media-amazon.com/images/I/519fbklBgrL.SS40_BG85,85,85_BR-120_PKdp-play-icon-overlay__.jpg"
        ],
        "triggers": {
          "rating": 4.5,
          "reviews_count": 3623,
          "discount_percent": 5,
          "original_price": 69.34,
          "discount_amount": 3.47,
          "has_prime": true
        },
        "score": 5.0,
        "deal_number": 12,
        "deal_id": "#012"
      },
      {
        "asin": "B0D2L5YFBG",
        "url": "https://www.amazon.fr/dp/B0D2L5YFBG",
        "title_preview": "",
        "price_flash": "Prix Flash: 63,48 €",
        "original_price": "Le plus bas : 74,99 €",
        "discount_text": "",
        "category": "Écrans PC",
        "has_prime": false,
        "title": "Ecran Portable 15.6 Pouces, Moniteur Portable 1080P FHD IPS, Écran Portatif avec Mini HDMI USB C, pour Laptop, PC, PS5, Xbox",
        "price": 63.48,
        "price_original": 74.99,
        "images": [
          "https://m.media-amazon.com/images/I/71MxrgXdo-L._AC_SL1500_.jpg",
          "https://m.media-amazon.com/images/I/51EbFEnVSnL.jpg",
          "https://m.media-amazon.com/images/I/51lOCGsAkNL.jpg",
          "https://m.media-amazon.com/images/I/518FiRE-6NL.jpg",
          "https://m.media-amazon.com/images/I/417xrLnSY0L.jpg",
          "https://m.media-amazon.com/images/I/51P49WbLwtL.jpg",
          "https://m.media-amazon.com/images/I/51cSD+-snGL.jpg",
          "https://m.media-amazon.com/images/I/51KA9DNZrLL.SS40_BG85,85,85_BR-120_PKdp-play-icon-overlay__.jpg"
        ],
        "triggers": {
          "rating": 4.4,
          "reviews_count": 464,
          "discount_percent": 15,
          "original_price": 74.99,
          "discount_amount": 11.51,
          "has_prime": true
        },
        "score": 4.5,
        "deal_number": 15,
        "deal_id": "#015"
      }
    ],
    "Entretien de la maison et nettoyage": [
      {
        "asin": "B0F3P4G6CK",
        "url": "https://www.amazon.fr/dp/B0F3P4G6CK",
        "title_preview": "",
        "price_flash": "Prix Flash: 19,50 €",
        "original_price": "Le plus bas : 22,48 €",
        "discount_text": "",
        "category": "Entretien de la maison et nettoyage",
        "has_prime": false,
        "title": "Lenor Adoucissant Lenor 216 Lavages (27x8), Parfum Envolée d’Air, 24H De Fraîcheur Relaxante, Avec Une Touche D’Huiles Essentielles, Testé Dermatologiquement, Fabriqué En France",
        "price": 19.5,
        "price_original": 22.48,
        "images": [
          "https://m.media-amazon.com/images/I/81rEr-01HmL._AC_SL1500_.jpg",
          "https://m.media-amazon.com/images/I/5181y9qBvRL.jpg",
          "https://m.media-amazon.com/images/I/51O7PUkJq+L.jpg",
          "https://m.media-amazon.com/images/I/51SDV2NIihL.jpg",
          "https://m.media-amazon.com/images/I/51voZI2yBEL.jpg",
          "https://m.media-amazon.com/images/I/41WcCEjy4YL.jpg",
          "https://m.media-amazon.com/images/I/51soO7UVf6L.jpg",
          "https://m.media-amazon.com/images/I/51wAn0vKl7L.jpg"
        ],
        "triggers": {
          "rating": 4.6,
          "reviews_count": 427,
          "discount_percent": 13,
          "original_price": 22.48,
          "discount_amount": 2.98,
          "has_prime": true
        },
        "score": 5.0,
        "deal_number": 13,
        "deal_id": "#013"
      }
    ],
    "Electronique embarquée": [
      {
        "asin": "B0F99N77VY",
        "url": "https://www.amazon.fr/dp/B0F99N77VY",
        "title_preview": "",
        "price_flash": "Prix Flash: 21,84 €",
        "original_price": "Le plus bas : 22,99 €",
        "discount_text": "",
        "category": "Electronique embarquée",
        "has_prime": false,
        "title": "S2 Mini Adaptateur CarPlay sans Fil pour iPhone, Convertissez Le Filaire en sans Fil, Plug & Play avec Typ-C/USB, Compatible avec Les Voitures à partir de 2016 et iOS 10+ (Noir)",
        "price": 21.84,
        "price_original": 22.99,
        "images": [
          "https://m.media-amazon.com/images/I/61VazYvuDAL._AC_SL1500_.jpg",
          "https://m.media-amazon.com/images/I/31iQEXODRTL.jpg",
          "https://m.media-amazon.com/images/I/41UWD3gNFdL.jpg",
          "https://m.media-amazon.com/images/I/41De+LJ-H+L.jpg",
          "https://m.media-amazon.com/images/I/41F6-AlN8HL.jpg",
          "https://m.media-amazon.com/images/I/512dilGsXUL.jpg",
          "https://m.media-amazon.com/images/I/41irEreFSvL.jpg",
          "https://m.media-amazon.com/images/I/71Tsxw+mRFL.SS40_BG85,85,85_BR-120_PKdp-play-icon-overlay__.jpg"
        ],
        "triggers": {
          "rating": 4.1,
          "reviews_count": 1131,
          "discount_percent": 5,
          "original_price": 22.99,
          "discount_amount": 1.15,
          "has_prime": true
        },
        "score": 4.5,
        "deal_number": 14,
        "deal_id": "#014"
      }
    ],
    "Technologie portable": [
      {
        "asin": "B0DPQ6QFWL",
        "url": "https://www.amazon.fr/dp/B0DPQ6QFWL",
        "title_preview": "",
        "price_flash": "Prix Flash: 47,49 €",
        "original_price": "Le plus bas : 49,99 €",
        "discount_text": "",
        "category": "Technologie portable",
        "has_prime": false,
        "title": "Montre Connectée Femme pour Samsung, iPhone, Android, 1.8\" Smartwatch avec Appel Bluetooth, Voix de l'IA, Alexa intégrée, Smartwatch Moniteur, Calories, IP68 Montre Intelligente, Podometre",
        "price": 47.49,
        "price_original": 49.99,
        "images": [
          "https://m.media-amazon.com/images/I/71GT31RwkgL._AC_SL1500_.jpg",
          "https://m.media-amazon.com/images/I/41Mucu1LeqL.jpg",
          "https://m.media-amazon.com/images/I/51CiwCq83+L.jpg",
          "https://m.media-amazon.com/images/I/41ml8LdOr3L.jpg",
          "https://m.media-amazon.com/images/I/41buQmq7fxL.jpg",
          "https://m.media-amazon.com/images/I/51vnl8ipodL.jpg",
          "https://m.media-amazon.com/images/I/415XZTXn8xL.jpg"
        ],
        "triggers": {
          "rating": 4.4,
          "reviews_count": 1480,
          "discount_percent": 5,
          "original_price": 49.99,
          "discount_amount": 2.5,
          "has_prime": true
        },
        "score": 4.5,
        "deal_number": 16,
        "deal_id": "#016"
      }
    ],
    "Petites fournitures": [
      {
        "asin": "B0CZMT61F7",
        "url": "https://www.amazon.fr/dp/B0CZMT61F7",
        "title_preview": "",
        "price_flash": "Prix Flash: 32,48 €",
        "original_price": "Le plus bas : 34,19 €",
        "discount_text": "",
        "category": "Petites fournitures",
        "has_prime": false,
        "title": "Souffleur Air Comprimé, 100000 TR/Min de Souffleur pc avec Batterie 9000mAh, Bombe Air Sec - Nettoyage PC, Plumeau Air Comprimé à 3 Vitessesavec Lumière LED pour Le Nettoyage de Canapé, Voiture",
        "price": 32.48,
        "price_original": 34.19,
        "images": [
          "https://m.media-amazon.com/images/I/71RF7SzJ-lL._AC_SL1500_.jpg",
          "https://m.media-amazon.com/images/I/51aMpoNfvbL.jpg",
          "https://m.media-amazon.com/images/I/41YnlZmbbyL.jpg",
          "https://m.media-amazon.com/images/I/51XwJNZncGL.jpg",
          "https://m.media-amazon.com/images/I/5150vgMKN9L.jpg",
          "https://m.media-amazon.com/images/I/51NyDna3mcL.jpg",
          "https://m.media-amazon.com/images/I/41WgLcU5NiL.jpg",
          "https://m.media-amazon.com/images/I/51bUHQ9UYHL.jpg"
        ],
        "triggers": {
          "rating": 4.3,
          "reviews_count": 1483,
          "discount_percent": 5,
          "original_price": 34.19,
          "discount_amount": 1.71,
          "has_prime": true
        },
        "score": 4.5,
        "deal_number": 17,
        "deal_id": "#017"
      }
    ],
    "Rasage et épilation": [
      {
        "asin": "B0DT493J7J",
        "url": "https://www.amazon.fr/dp/B0DT493J7J",
        "title_preview": "",
        "price_flash": "Prix Flash: 56,90 €",
        "original_price": "Le plus bas : 61,66 €",
        "discount_text": "",
        "category": "Rasage et épilation",
        "has_prime": false,
        "title": "Gillette Lot De 20 Recharges De Rasoir Pour Hommes Proglide, AUTHENTIQUES, Cartouche A 5 Lames Ultra-Affutées, Nouvelle Lubrification, Bande Lubrifiante x2, Rasage Du Visage Flexible",
        "price": 56.9,
        "price_original": 61.66,
        "images": [
          "https://m.media-amazon.com/images/I/71z3LW5SjOL._AC_SL1500_.jpg",
          "https://m.media-amazon.com/images/I/41ZDH7CHNyL.jpg",
          "https://m.media-amazon.com/images/I/41etcejAa4L.jpg",
          "https://m.media-amazon.com/images/I/511SvYkf0TL.jpg",
          "https://m.media-amazon.com/images/I/41kPY1-sc3L.jpg",
          "https://m.media-amazon.com/images/I/51qrx3-0q2L.jpg",
          "https://m.media-amazon.com/images/I/41djUQhlFTL.jpg",
          "https://m.media-amazon.com/images/I/51owtod6IYL.jpg"
        ],
        "triggers": {
          "rating": 4.6,
          "reviews_count": 871,
          "discount_percent": 8,
          "original_price": 61.66,
          "discount_amount": 4.76,
          "has_prime": true
        },
        "score": 4.0,
        "deal_number": 19,
        "deal_id": "#019"
      }
    ],
    "Mobilier de jardin": [
      {
        "asin": "B08BQXK62C",
        "url": "https://www.amazon.fr/dp/B08BQXK62C",
        "title_preview": "",
        "price_flash": "Prix Flash: 679,79 €",
        "original_price": "Le plus bas : 759,90 €",
        "discount_text": "",
        "category": "Mobilier de jardin",
        "has_prime": false,
        "title": "tectake® Ensemble de 4 Fauteuils Confortables avec Accoudoirs, Salon de Jardin Exterieur ou Intérieur, PolyRotin et Aluminium, Coussins Inclus, Mobilier de Jardin Amenagement Balcon Terrasse Veranda",
        "price": 679.79,
        "price_original": 759.9,
        "images": [
          "https://m.media-amazon.com/images/I/81jOjDCPwsL._AC_SL1350_.jpg",
          "https://m.media-amazon.com/images/I/51T7WOLKF6L.jpg",
          "https://m.media-amazon.com/images/I/51KoALCFQFL.jpg",
          "https://m.media-amazon.com/images/I/41ODoSeYvlL.jpg",
          "https://m.media-amazon.com/images/I/51EbkvXdwdL.jpg",
          "https://m.media-amazon.com/images/I/41trrPEXBDL.jpg",
          "https://m.media-amazon.com/images/I/51POCSS7w6L.jpg",
          "https://m.media-amazon.com/images/I/51ipY7b8J4L.jpg"
        ],
        "triggers": {
          "rating": 4.4,
          "reviews_count": 147,
          "discount_percent": 11,
          "original_price": 759.9,
          "discount_amount": 80.11,
          "has_prime": true
        },
        "score": 4.0,
        "deal_number": 20,
        "deal_id": "#020"
      }
    ],
    "Piscines, bains à remous et accessoires": [
      {
        "asin": "B0FMY1NP6T",
        "url": "https://www.amazon.fr/dp/B0FMY1NP6T",
        "title_preview": "",
        "price_flash": "Prix Flash: 123,49 €",
        "original_price": "Le plus bas : 129,99 €",
        "discount_text": "",
        "category": "Piscines, bains à remous et accessoires",
        "has_prime": false,
        "title": "WINNY POOL CLEANER Winny 200 Robot Piscine, Aspirateur Piscine sans Fil avec Batterie, Autonomie 75 Min pour Piscines Hors-Sol 60m², Double Filtration,Stationnement Automatique(Transparent Noir)",
        "price": 123.49,
        "price_original": 129.99,
        "images": [
          "https://m.media-amazon.com/images/I/71pRFPjIRXL._AC_SL1500_.jpg",
          "https://m.media-amazon.com/images/I/41pXJF5Nm8L.jpg",
          "https://m.media-amazon.com/images/I/51FS7nPvDWL.jpg",
          "https://m.media-amazon.com/images/I/51t73Jdp+KL.jpg",
          "https://m.media-amazon.com/images/I/51PJkO5SOqL.jpg",
          "https://m.media-amazon.com/images/I/512r9dl8JML.jpg",
          "https://m.media-amazon.com/images/I/5137czlCOnL.jpg"
        ],
        "triggers": {
          "rating": 4.6,
          "reviews_count": 322,
          "discount_percent": 5,
          "original_price": 129.99,
          "discount_amount": 6.5,
          "has_prime": true
        },
        "score": 4.0,
        "deal_number": 21,
        "deal_id": "#021"
      }
    ],
    "Imprimantes et accessoires": [
      {
        "asin": "B0G381QW1X",
        "url": "https://www.amazon.fr/dp/B0G381QW1X",
        "title_preview": "",
        "price_flash": "Prix Flash: 94,99 €",
        "original_price": "Le plus bas : 99,99 €",
        "discount_text": "",
        "category": "Imprimantes et accessoires",
        "has_prime": false,
        "title": "Cartouche 937XL 937 9730e Compatible pour HP 937 Pack de 4 Cartouche XL 937e pour HP OfficeJet Pro 9730e 9120e 9720e 9132e 9122e 9120b 9125e 9130b 9130e 9720 9730 Imprimantes (Noir Cyan Jaune Magenta)",
        "price": 94.99,
        "price_original": 99.99,
        "images": [
          "https://m.media-amazon.com/images/I/71e35Sb2N7L._AC_SL1500_.jpg",
          "https://m.media-amazon.com/images/I/51aDMwvPViL.jpg",
          "https://m.media-amazon.com/images/I/41X2BKlj4EL.jpg",
          "https://m.media-amazon.com/images/I/51pf7VKZZNL.jpg",
          "https://m.media-amazon.com/images/I/41Xn4SVLtfL.jpg",
          "https://m.media-amazon.com/images/I/51aE2q7Aq1L.jpg",
          "https://m.media-amazon.com/images/I/41hihKVgjBL.jpg",
          "https://m.media-amazon.com/images/I/51VsCF1QOXL.SS40_BG85,85,85_BR-120_PKdp-play-icon-overlay__.jpg"
        ],
        "triggers": {
          "rating": 4.6,
          "reviews_count": 66,
          "discount_percent": 5,
          "original_price": 99.99,
          "discount_amount": 5,
          "has_prime": true
        },
        "score": 3.5,
        "deal_number": 22,
        "deal_id": "#022"
      }
    ],
    "Ordinateurs portables": [
      {
        "asin": "B0G4CQ2JCD",
        "url": "https://www.amazon.fr/dp/B0G4CQ2JCD",
        "title_preview": "",
        "price_flash": "Prix Flash: 370,49 €",
        "original_price": "Le plus bas : 459,99 €",
        "discount_text": "",
        "category": "Ordinateurs portables",
        "has_prime": false,
        "title": "18,5\" PC Portable, FHD Ordinateur Portable Processeur Quad-Core 13ème N150 Jusqu'à 3,60GHz, 16GB RAM + 512GB SSD M.2, Wi-FI Dual-Band, BT 5.2, USB 3.2, HDMI, Type-C, Batterie Longue 8000mAh",
        "price": 370.49,
        "price_original": 459.99,
        "images": [
          "https://m.media-amazon.com/images/I/71za5XiEdKL._AC_SL1500_.jpg",
          "https://m.media-amazon.com/images/I/51UfKtrOtzL.jpg",
          "https://m.media-amazon.com/images/I/51cXFTo+i6L.jpg",
          "https://m.media-amazon.com/images/I/51XEphae5vL.jpg",
          "https://m.media-amazon.com/images/I/41ugzvzFsYL.jpg",
          "https://m.media-amazon.com/images/I/41zprFmeEXL.jpg",
          "https://m.media-amazon.com/images/I/41xTqk68teL.jpg",
          "https://m.media-amazon.com/images/I/51MLi2q6ijL.SS40_BG85,85,85_BR-120_PKdp-play-icon-overlay__.jpg"
        ],
        "triggers": {
          "rating": 4.4,
          "reviews_count": 13,
          "discount_percent": 19,
          "original_price": 459.99,
          "discount_amount": 89.5,
          "has_prime": true
        },
        "score": 3.5,
        "deal_number": 23,
        "deal_id": "#023"
      }
    ],
    "Produits professionnels de sécurité et de santé": [
      {
        "asin": "B096W8645Q",
        "url": "https://www.amazon.fr/dp/B096W8645Q",
        "title_preview": "",
        "price_flash": "Prix Flash: 79,34 €",
        "original_price": "Le plus bas : 83,52 €",
        "discount_text": "",
        "category": "Produits professionnels de sécurité et de santé",
        "has_prime": false,
        "title": "SPC® by Brady Kit Anti-Pollution Chimique – Kit Absorbant Chimique pour Déversements de Produits Chimiques Dangereux, Inclus 10 Feuilles Absorbantes Chimiques, 2 Boudins, Gants et Sac de Déchet",
        "price": 79.34,
        "price_original": 83.52,
        "images": [
          "https://m.media-amazon.com/images/I/81MFQSw5mUL._AC_SL1500_.jpg",
          "https://m.media-amazon.com/images/I/41iqsv2AW6L.jpg",
          "https://m.media-amazon.com/images/I/41M2xXJ1nXL.jpg",
          "https://m.media-amazon.com/images/I/51cwDaXmvCL.jpg"
        ],
        "triggers": {
          "rating": 4.8,
          "reviews_count": 6,
          "discount_percent": 5,
          "original_price": 83.52,
          "discount_amount": 4.18,
          "has_prime": true
        },
        "score": 3.0,
        "deal_number": 25,
        "deal_id": "#025"
      }
    ]
  },
  "all_products": [
    {
      "asin": "B0FSL2L7LW",
      "url": "https://www.amazon.fr/dp/B0FSL2L7LW",
      "title_preview": "",
      "price_flash": "Prix Flash: 299,98 €",
      "original_price": "Le plus bas : 999,99 €",
      "discount_text": "",
      "category": "Aspirateurs, entretien des sols et nettoyeurs de vitres",
      "has_prime": false,
      "title": "Lefant M3 Robot Aspirateur Laveur 12 000 Pa, Station Multifonctionnelle, Double Serpillière Rotative 200 TR/Min, Navigation dToF, Évitement d'obstacles PSD, 220min, 30 réglages de Niveau d'eau",
      "price": 299.98,
      "price_original": 999.99,
      "images": [
        "https://m.media-amazon.com/images/I/71i35ufWOXL._AC_SL1500_.jpg",
        "https://m.media-amazon.com/images/I/41q7yOd0YyL.jpg",
        "https://m.media-amazon.com/images/I/41G9RD2oc4L.jpg",
        "https://m.media-amazon.com/images/I/41Q2igEWjpL.jpg",
        "https://m.media-amazon.com/images/I/416l028hncL.jpg",
        "https://m.media-amazon.com/images/I/51wIsstigzL.jpg",
        "https://m.media-amazon.com/images/I/51H2s-fJbPL.jpg",
        "https://m.media-amazon.com/images/I/41i7pvoAzQL.jpg"
      ],
      "triggers": {
        "rating": 4.3,
        "reviews_count": 2607,
        "discount_percent": 70,
        "original_price": 999.99,
        "discount_amount": 700.01,
        "has_prime": true
      },
      "score": 7.5,
      "deal_number": 1,
      "deal_id": "#001"
    },
    {
      "asin": "B091GB1NP1",
      "url": "https://www.amazon.fr/dp/B091GB1NP1",
      "title_preview": "",
      "price_flash": "Prix Flash: 18,99 €",
      "original_price": "Le plus bas : 22,99 €",
      "discount_text": "",
      "category": "Vitamines, minéraux et compléments",
      "has_prime": false,
      "title": "Vitamine D3 K2 MK7, 365 Micro-Comprimés Végétariens (pour 1 An), Combinaison Vit D3 2000UI Cholécalciférol avec Vitamine K2 MK7 200μg Ménaquinone, sans Stéarate de Magnésium",
      "price": 18.99,
      "price_original": 22.99,
      "images": [
        "https://m.media-amazon.com/images/I/71dQNhLYgeL._AC_SL1500_.jpg",
        "https://m.media-amazon.com/images/I/41AdssjR5pL.jpg",
        "https://m.media-amazon.com/images/I/41lFe6LTfQL.jpg",
        "https://m.media-amazon.com/images/I/41+nkFa3CyL.jpg",
        "https://m.media-amazon.com/images/I/516H24Q0E8L.jpg",
        "https://m.media-amazon.com/images/I/51NPKIixE8L.jpg",
        "https://m.media-amazon.com/images/I/41OSJW1YJHL.jpg",
        "https://m.media-amazon.com/images/I/31pl4d8ydVL.jpg"
      ],
      "triggers": {
        "rating": 4.5,
        "reviews_count": 6417,
        "discount_percent": 17,
        "original_price": 22.99,
        "discount_amount": 4,
        "has_prime": true
      },
      "score": 7.0,
      "deal_number": 2,
      "deal_id": "#002"
    },
    {
      "asin": "B075JMFTB8",
      "url": "https://www.amazon.fr/dp/B075JMFTB8",
      "title_preview": "",
      "price_flash": "Prix Flash: 26,50 €",
      "original_price": "Le plus bas : 27,90 €",
      "discount_text": "",
      "category": "Ameublement et décoration",
      "has_prime": false,
      "title": "Utopia Bedding Couette 220x240 cm, Couette Chaud 370 GSM, pour lit 2 Personne, Couverture Blanc avec Onglets d'angle (Blanc)",
      "price": 26.5,
      "price_original": 27.9,
      "images": [
        "https://m.media-amazon.com/images/I/81MuXSwe-ZL._AC_SL1500_.jpg",
        "https://m.media-amazon.com/images/I/51i7V-2KJ7L.jpg",
        "https://m.media-amazon.com/images/I/31NP3zWi+QL.jpg",
        "https://m.media-amazon.com/images/I/41f5igACPML.jpg",
        "https://m.media-amazon.com/images/I/31Prnrf+rVL.jpg"
      ],
      "triggers": {
        "rating": 4.5,
        "reviews_count": 39434,
        "discount_percent": 5,
        "original_price": 27.9,
        "discount_amount": 1.4,
        "has_prime": true
      },
      "score": 7.0,
      "deal_number": 3,
      "deal_id": "#003"
    },
    {
      "asin": "B07CB94N28",
      "url": "https://www.amazon.fr/dp/B07CB94N28",
      "title_preview": "",
      "price_flash": "Prix Flash: 11,99 €",
      "original_price": "Le plus bas : 12,62 €",
      "discount_text": "",
      "category": "Ameublement et décoration",
      "has_prime": false,
      "title": "Utopia Bedding Drap Housse - Gris, 160 x 200 cm - Coupes de 35 cm pour Matelas épais - Polyester Microfibre brossée",
      "price": 11.99,
      "price_original": 12.62,
      "images": [
        "https://m.media-amazon.com/images/I/71k1qAeLoAL._AC_SL1500_.jpg",
        "https://m.media-amazon.com/images/I/41w1GUR+66L.jpg",
        "https://m.media-amazon.com/images/I/41FM-SawD0L.jpg",
        "https://m.media-amazon.com/images/I/41DuaiF+lZL.jpg",
        "https://m.media-amazon.com/images/I/41LfnP4PThL.jpg",
        "https://m.media-amazon.com/images/I/51+SnG-KPOL.jpg",
        "https://m.media-amazon.com/images/I/41FSLnmYy9L.jpg"
      ],
      "triggers": {
        "rating": 4.6,
        "reviews_count": 161412,
        "discount_percent": 5,
        "original_price": 12.62,
        "discount_amount": 0.63,
        "has_prime": true
      },
      "score": 7.0,
      "deal_number": 4,
      "deal_id": "#004"
    },
    {
      "asin": "B0CYPY3G8B",
      "url": "https://www.amazon.fr/dp/B0CYPY3G8B",
      "title_preview": "",
      "price_flash": "Prix Flash: 18,86 €",
      "original_price": "Le plus bas : 19,85 €",
      "discount_text": "",
      "category": "Ameublement et décoration",
      "has_prime": false,
      "title": "Utopia Bedding Housse De Matelas 140 x 190 x 20 cm Imperméable Avec Fermeture éclair, Certifié Oeko-TEX, Protégé Matelas, Blanc",
      "price": 18.86,
      "price_original": 19.85,
      "images": [
        "https://m.media-amazon.com/images/I/71-sHDrPc0L._AC_SL1500_.jpg",
        "https://m.media-amazon.com/images/I/41xQPZwIqQL.jpg",
        "https://m.media-amazon.com/images/I/413eOXUvr1L.jpg",
        "https://m.media-amazon.com/images/I/51NUWDrI-HL.jpg",
        "https://m.media-amazon.com/images/I/51j+IfgS8aL.jpg",
        "https://m.media-amazon.com/images/I/51Z-+aeEBML.jpg",
        "https://m.media-amazon.com/images/I/51nmdf7OUCL.jpg"
      ],
      "triggers": {
        "rating": 4.5,
        "reviews_count": 22675,
        "discount_percent": 5,
        "original_price": 19.85,
        "discount_amount": 0.99,
        "has_prime": true
      },
      "score": 7.0,
      "deal_number": 5,
      "deal_id": "#005"
    },
    {
      "asin": "B0G1XZHT7F",
      "url": "https://www.amazon.fr/dp/B0G1XZHT7F",
      "title_preview": "",
      "price_flash": "Prix Flash: 29,99 €",
      "original_price": "Le plus bas : 79,99 €",
      "discount_text": "",
      "category": "GPS et accessoires",
      "has_prime": false,
      "title": "Lot de 4 Traceur Tag Android & iOS, Compatible avec Apple Find My et Google Find Hub, Tracker GPS Android & iOS avec Batterie remplaçable, Traceur GPS Android pour Portefeuilles/Valises/Clés/Bagages",
      "price": 29.99,
      "price_original": 79.99,
      "images": [
        "https://m.media-amazon.com/images/I/71VNWKQ4dNL._AC_SL1500_.jpg",
        "https://m.media-amazon.com/images/I/41DHAiif++L.jpg",
        "https://m.media-amazon.com/images/I/41ptFpopxSL.jpg",
        "https://m.media-amazon.com/images/I/417JKvlvoTL.jpg",
        "https://m.media-amazon.com/images/I/41srHehr32L.jpg",
        "https://m.media-amazon.com/images/I/412gZSQBbeL.jpg",
        "https://m.media-amazon.com/images/I/41o+06a3EKL.jpg",
        "https://m.media-amazon.com/images/I/41clrCFwKnL.jpg"
      ],
      "triggers": {
        "rating": 4.6,
        "reviews_count": 172,
        "discount_percent": 63,
        "original_price": 79.99,
        "discount_amount": 50,
        "has_prime": true
      },
      "score": 6.5,
      "deal_number": 6,
      "deal_id": "#006"
    },
    {
      "asin": "B0CY1ZSQZ5",
      "url": "https://www.amazon.fr/dp/B0CY1ZSQZ5",
      "title_preview": "",
      "price_flash": "Prix Flash: 30,39 €",
      "original_price": "Le plus bas : 31,99 €",
      "discount_text": "",
      "category": "Bagages, sacs de voyage et accessoires",
      "has_prime": false,
      "title": "KLOSTAIN Sac à Dos Voyage Cabine Avion 45x36x20 pour Easyjet 30L Bagage Cabine Grande Bagage à Main sous Le Siège Sac à Dos Homme pour Ordinateur Portable 14 Noir",
      "price": 30.39,
      "price_original": 31.99,
      "images": [
        "https://m.media-amazon.com/images/I/81NCrngO16L._AC_SL1500_.jpg",
        "https://m.media-amazon.com/images/I/41eVXcSny9L.jpg",
        "https://m.media-amazon.com/images/I/511+uboryjL.jpg",
        "https://m.media-amazon.com/images/I/51Ggh9q2eWL.jpg",
        "https://m.media-amazon.com/images/I/51QyRa0gNiL.jpg",
        "https://m.media-amazon.com/images/I/51jGf3wrwgL.jpg",
        "https://m.media-amazon.com/images/I/412GrtlGEtL.jpg",
        "https://m.media-amazon.com/images/I/71bY-DPmn0L.SS40_BG85,85,85_BR-120_PKdp-play-icon-overlay__.jpg"
      ],
      "triggers": {
        "rating": 4.7,
        "reviews_count": 6799,
        "discount_percent": 5,
        "original_price": 31.99,
        "discount_amount": 1.6,
        "has_prime": true
      },
      "score": 6.0,
      "deal_number": 7,
      "deal_id": "#007"
    },
    {
      "asin": "B00MNBQ742",
      "url": "https://www.amazon.fr/dp/B00MNBQ742",
      "title_preview": "",
      "price_flash": "Prix Flash: 74,99 €",
      "original_price": "Le plus bas : 79,99 €",
      "discount_text": "",
      "category": "Petit électroménager",
      "has_prime": false,
      "title": "Moulinex Blender chauffant, 1000 W, Capacité 1.2 L, 5 programmes automatiques, Double paroi, Soupe, Velouté, Compote, Smoothie, Maintien au Chaud, Easy Soup silver LM841110",
      "price": 74.99,
      "price_original": 79.99,
      "images": [
        "https://m.media-amazon.com/images/I/71O84i1ENfL._AC_SL1500_.jpg",
        "https://m.media-amazon.com/images/I/41XzNkhFU2L.jpg",
        "https://m.media-amazon.com/images/I/512ZCgHWyIL.jpg",
        "https://m.media-amazon.com/images/I/31UyUaX+7dL.jpg",
        "https://m.media-amazon.com/images/I/510SFnA5ekL.jpg",
        "https://m.media-amazon.com/images/I/51Qdvuh+AoL.jpg",
        "https://m.media-amazon.com/images/I/41QcBCAuEiL.jpg"
      ],
      "triggers": {
        "rating": 4.5,
        "reviews_count": 6672,
        "discount_percent": 6,
        "original_price": 79.99,
        "discount_amount": 5,
        "has_prime": true
      },
      "score": 6.0,
      "deal_number": 8,
      "deal_id": "#008"
    },
    {
      "asin": "B0C9MBG966",
      "url": "https://www.amazon.fr/dp/B0C9MBG966",
      "title_preview": "",
      "price_flash": "Prix Flash: 52,99 €",
      "original_price": "Le plus bas : 62,90 €",
      "discount_text": "",
      "category": "Ameublement et décoration",
      "has_prime": false,
      "title": "Novilla Surmatelas 140 X 190 CM, Surmatelas en Mousse à Mémoire de Forme Gel, Épaisseur 5 CM, avec Design Antidérapant et Certification de Sécurité, sans Odeur, Housse Lavable",
      "price": 52.99,
      "price_original": 62.9,
      "images": [
        "https://m.media-amazon.com/images/I/61mgKAGSboL._AC_SL1500_.jpg",
        "https://m.media-amazon.com/images/I/31iln7wqGDL.jpg",
        "https://m.media-amazon.com/images/I/41nOOdPhJCL.jpg",
        "https://m.media-amazon.com/images/I/41O0d1MnAAL.jpg",
        "https://m.media-amazon.com/images/I/411KHqcmuaL.jpg",
        "https://m.media-amazon.com/images/I/41+3YkczE2L.jpg",
        "https://m.media-amazon.com/images/I/41cBwupnkpL.jpg"
      ],
      "triggers": {
        "rating": 4.5,
        "reviews_count": 1854,
        "discount_percent": 16,
        "original_price": 62.9,
        "discount_amount": 9.91,
        "has_prime": true
      },
      "score": 6.0,
      "deal_number": 9,
      "deal_id": "#009"
    },
    {
      "asin": "B0G2YVZMHQ",
      "url": "https://www.amazon.fr/dp/B0G2YVZMHQ",
      "title_preview": "",
      "price_flash": "Prix Flash: 110,99 €",
      "original_price": "Le plus bas : 116,99 €",
      "discount_text": "",
      "category": "Rangement et organisation",
      "has_prime": false,
      "title": "Leifheit Séchoir parapluie Linomatic 500 Deluxe, étendoir à linge avec rétractation automatique des fils, étendoir à linge extérieur avec 50m de fil, jusqu'à 5 machines à laver, douille de sol incluse",
      "price": 110.99,
      "price_original": 116.99,
      "images": [
        "https://m.media-amazon.com/images/I/51PVgcpg3wL._AC_SL1227_.jpg",
        "https://m.media-amazon.com/images/I/31sD5jl8fVL.jpg",
        "https://m.media-amazon.com/images/I/51B3ydjtOlL.jpg",
        "https://m.media-amazon.com/images/I/41DG-csglAL.jpg",
        "https://m.media-amazon.com/images/I/41BvUIwPqWL.jpg",
        "https://m.media-amazon.com/images/I/51hGWTjp+HL.jpg",
        "https://m.media-amazon.com/images/I/51YR4hN1quL.jpg"
      ],
      "triggers": {
        "rating": 4.5,
        "reviews_count": 7804,
        "discount_percent": 5,
        "original_price": 116.99,
        "discount_amount": 6,
        "has_prime": true
      },
      "score": 6.0,
      "deal_number": 10,
      "deal_id": "#010"
    },
    {
      "asin": "B0D5D55GXL",
      "url": "https://www.amazon.fr/dp/B0D5D55GXL",
      "title_preview": "",
      "price_flash": "Prix Flash: 215,00 €",
      "original_price": "Le plus bas : 269,99 €",
      "discount_text": "",
      "category": "Hygiène dentaire",
      "has_prime": false,
      "title": "Oral-B iO Série 9 Brosse à Dents Électrique Noire, Capteur De Pression, Modes Soin Des Gencives, Douceur Pour Protéger Des Dents Sensibles, 3 Têtes De Recharge, 1 Chargeur, 1 Étui De Voyage, En Carton",
      "price": 215,
      "price_original": 269.99,
      "images": [
        "https://m.media-amazon.com/images/I/611Z5K46KSL._AC_SL1100_.jpg",
        "https://m.media-amazon.com/images/I/41o8ZhOaxZL.jpg",
        "https://m.media-amazon.com/images/I/515u4bTmaTL.jpg",
        "https://m.media-amazon.com/images/I/51tGsXk4B+L.jpg",
        "https://m.media-amazon.com/images/I/41fLKSyCoWL.jpg",
        "https://m.media-amazon.com/images/I/51g5Atc18nL.jpg",
        "https://m.media-amazon.com/images/I/51qLDMWvTJL.jpg",
        "https://m.media-amazon.com/images/I/41UsLtGICbL.SS40_BG85,85,85_BR-120_PKdp-play-icon-overlay__.jpg"
      ],
      "triggers": {
        "rating": 4.6,
        "reviews_count": 197,
        "discount_percent": 20,
        "original_price": 269.99,
        "discount_amount": 54.99,
        "has_prime": true
      },
      "score": 5.0,
      "deal_number": 11,
      "deal_id": "#011"
    },
    {
      "asin": "B0FY2NRCYR",
      "url": "https://www.amazon.fr/dp/B0FY2NRCYR",
      "title_preview": "",
      "price_flash": "Prix Flash: 65,87 €",
      "original_price": "Le plus bas : 69,34 €",
      "discount_text": "",
      "category": "Écrans PC",
      "has_prime": false,
      "title": "Ingnok Écran Portable 15,6\", FHD 1080P IPS Moniteur Portable avec Haut-parleurs Intégré, Ultra-Leger Ecran Portatif pour Ordinateur Portable/PC/Mac/PS3/4/5/X-box - Connectivité USB C et HDMI",
      "price": 65.87,
      "price_original": 69.34,
      "images": [
        "https://m.media-amazon.com/images/I/71PYfOBmAkL._AC_SL1500_.jpg",
        "https://m.media-amazon.com/images/I/41rtVrh0lIL.jpg",
        "https://m.media-amazon.com/images/I/51PnxKNNv6L.jpg",
        "https://m.media-amazon.com/images/I/51KccidT0LL.jpg",
        "https://m.media-amazon.com/images/I/41F-HrlLXlL.jpg",
        "https://m.media-amazon.com/images/I/519Zs4HFk-L.jpg",
        "https://m.media-amazon.com/images/I/51LZerfnaML.jpg",
        "https://m.media-amazon.com/images/I/519fbklBgrL.SS40_BG85,85,85_BR-120_PKdp-play-icon-overlay__.jpg"
      ],
      "triggers": {
        "rating": 4.5,
        "reviews_count": 3623,
        "discount_percent": 5,
        "original_price": 69.34,
        "discount_amount": 3.47,
        "has_prime": true
      },
      "score": 5.0,
      "deal_number": 12,
      "deal_id": "#012"
    },
    {
      "asin": "B0F3P4G6CK",
      "url": "https://www.amazon.fr/dp/B0F3P4G6CK",
      "title_preview": "",
      "price_flash": "Prix Flash: 19,50 €",
      "original_price": "Le plus bas : 22,48 €",
      "discount_text": "",
      "category": "Entretien de la maison et nettoyage",
      "has_prime": false,
      "title": "Lenor Adoucissant Lenor 216 Lavages (27x8), Parfum Envolée d’Air, 24H De Fraîcheur Relaxante, Avec Une Touche D’Huiles Essentielles, Testé Dermatologiquement, Fabriqué En France",
      "price": 19.5,
      "price_original": 22.48,
      "images": [
        "https://m.media-amazon.com/images/I/81rEr-01HmL._AC_SL1500_.jpg",
        "https://m.media-amazon.com/images/I/5181y9qBvRL.jpg",
        "https://m.media-amazon.com/images/I/51O7PUkJq+L.jpg",
        "https://m.media-amazon.com/images/I/51SDV2NIihL.jpg",
        "https://m.media-amazon.com/images/I/51voZI2yBEL.jpg",
        "https://m.media-amazon.com/images/I/41WcCEjy4YL.jpg",
        "https://m.media-amazon.com/images/I/51soO7UVf6L.jpg",
        "https://m.media-amazon.com/images/I/51wAn0vKl7L.jpg"
      ],
      "triggers": {
        "rating": 4.6,
        "reviews_count": 427,
        "discount_percent": 13,
        "original_price": 22.48,
        "discount_amount": 2.98,
        "has_prime": true
      },
      "score": 5.0,
      "deal_number": 13,
      "deal_id": "#013"
    },
    {
      "asin": "B0F99N77VY",
      "url": "https://www.amazon.fr/dp/B0F99N77VY",
      "title_preview": "",
      "price_flash": "Prix Flash: 21,84 €",
      "original_price": "Le plus bas : 22,99 €",
      "discount_text": "",
      "category": "Electronique embarquée",
      "has_prime": false,
      "title": "S2 Mini Adaptateur CarPlay sans Fil pour iPhone, Convertissez Le Filaire en sans Fil, Plug & Play avec Typ-C/USB, Compatible avec Les Voitures à partir de 2016 et iOS 10+ (Noir)",
      "price": 21.84,
      "price_original": 22.99,
      "images": [
        "https://m.media-amazon.com/images/I/61VazYvuDAL._AC_SL1500_.jpg",
        "https://m.media-amazon.com/images/I/31iQEXODRTL.jpg",
        "https://m.media-amazon.com/images/I/41UWD3gNFdL.jpg",
        "https://m.media-amazon.com/images/I/41De+LJ-H+L.jpg",
        "https://m.media-amazon.com/images/I/41F6-AlN8HL.jpg",
        "https://m.media-amazon.com/images/I/512dilGsXUL.jpg",
        "https://m.media-amazon.com/images/I/41irEreFSvL.jpg",
        "https://m.media-amazon.com/images/I/71Tsxw+mRFL.SS40_BG85,85,85_BR-120_PKdp-play-icon-overlay__.jpg"
      ],
      "triggers": {
        "rating": 4.1,
        "reviews_count": 1131,
        "discount_percent": 5,
        "original_price": 22.99,
        "discount_amount": 1.15,
        "has_prime": true
      },
      "score": 4.5,
      "deal_number": 14,
      "deal_id": "#014"
    },
    {
      "asin": "B0D2L5YFBG",
      "url": "https://www.amazon.fr/dp/B0D2L5YFBG",
      "title_preview": "",
      "price_flash": "Prix Flash: 63,48 €",
      "original_price": "Le plus bas : 74,99 €",
      "discount_text": "",
      "category": "Écrans PC",
      "has_prime": false,
      "title": "Ecran Portable 15.6 Pouces, Moniteur Portable 1080P FHD IPS, Écran Portatif avec Mini HDMI USB C, pour Laptop, PC, PS5, Xbox",
      "price": 63.48,
      "price_original": 74.99,
      "images": [
        "https://m.media-amazon.com/images/I/71MxrgXdo-L._AC_SL1500_.jpg",
        "https://m.media-amazon.com/images/I/51EbFEnVSnL.jpg",
        "https://m.media-amazon.com/images/I/51lOCGsAkNL.jpg",
        "https://m.media-amazon.com/images/I/518FiRE-6NL.jpg",
        "https://m.media-amazon.com/images/I/417xrLnSY0L.jpg",
        "https://m.media-amazon.com/images/I/51P49WbLwtL.jpg",
        "https://m.media-amazon.com/images/I/51cSD+-snGL.jpg",
        "https://m.media-amazon.com/images/I/51KA9DNZrLL.SS40_BG85,85,85_BR-120_PKdp-play-icon-overlay__.jpg"
      ],
      "triggers": {
        "rating": 4.4,
        "reviews_count": 464,
        "discount_percent": 15,
        "original_price": 74.99,
        "discount_amount": 11.51,
        "has_prime": true
      },
      "score": 4.5,
      "deal_number": 15,
      "deal_id": "#015"
    },
    {
      "asin": "B0DPQ6QFWL",
      "url": "https://www.amazon.fr/dp/B0DPQ6QFWL",
      "title_preview": "",
      "price_flash": "Prix Flash: 47,49 €",
      "original_price": "Le plus bas : 49,99 €",
      "discount_text": "",
      "category": "Technologie portable",
      "has_prime": false,
      "title": "Montre Connectée Femme pour Samsung, iPhone, Android, 1.8\" Smartwatch avec Appel Bluetooth, Voix de l'IA, Alexa intégrée, Smartwatch Moniteur, Calories, IP68 Montre Intelligente, Podometre",
      "price": 47.49,
      "price_original": 49.99,
      "images": [
        "https://m.media-amazon.com/images/I/71GT31RwkgL._AC_SL1500_.jpg",
        "https://m.media-amazon.com/images/I/41Mucu1LeqL.jpg",
        "https://m.media-amazon.com/images/I/51CiwCq83+L.jpg",
        "https://m.media-amazon.com/images/I/41ml8LdOr3L.jpg",
        "https://m.media-amazon.com/images/I/41buQmq7fxL.jpg",
        "https://m.media-amazon.com/images/I/51vnl8ipodL.jpg",
        "https://m.media-amazon.com/images/I/415XZTXn8xL.jpg"
      ],
      "triggers": {
        "rating": 4.4,
        "reviews_count": 1480,
        "discount_percent": 5,
        "original_price": 49.99,
        "discount_amount": 2.5,
        "has_prime": true
      },
      "score": 4.5,
      "deal_number": 16,
      "deal_id": "#016"
    },
    {
      "asin": "B0CZMT61F7",
      "url": "https://www.amazon.fr/dp/B0CZMT61F7",
      "title_preview": "",
      "price_flash": "Prix Flash: 32,48 €",
      "original_price": "Le plus bas : 34,19 €",
      "discount_text": "",
      "category": "Petites fournitures",
      "has_prime": false,
      "title": "Souffleur Air Comprimé, 100000 TR/Min de Souffleur pc avec Batterie 9000mAh, Bombe Air Sec - Nettoyage PC, Plumeau Air Comprimé à 3 Vitessesavec Lumière LED pour Le Nettoyage de Canapé, Voiture",
      "price": 32.48,
      "price_original": 34.19,
      "images": [
        "https://m.media-amazon.com/images/I/71RF7SzJ-lL._AC_SL1500_.jpg",
        "https://m.media-amazon.com/images/I/51aMpoNfvbL.jpg",
        "https://m.media-amazon.com/images/I/41YnlZmbbyL.jpg",
        "https://m.media-amazon.com/images/I/51XwJNZncGL.jpg",
        "https://m.media-amazon.com/images/I/5150vgMKN9L.jpg",
        "https://m.media-amazon.com/images/I/51NyDna3mcL.jpg",
        "https://m.media-amazon.com/images/I/41WgLcU5NiL.jpg",
        "https://m.media-amazon.com/images/I/51bUHQ9UYHL.jpg"
      ],
      "triggers": {
        "rating": 4.3,
        "reviews_count": 1483,
        "discount_percent": 5,
        "original_price": 34.19,
        "discount_amount": 1.71,
        "has_prime": true
      },
      "score": 4.5,
      "deal_number": 17,
      "deal_id": "#017"
    },
    {
      "asin": "B0G1XFDP75",
      "url": "https://www.amazon.fr/dp/B0G1XFDP75",
      "title_preview": "",
      "price_flash": "Prix Flash: 179,99 €",
      "original_price": "Le plus bas : 189,99 €",
      "discount_text": "",
      "category": "Aspirateurs, entretien des sols et nettoyeurs de vitres",
      "has_prime": false,
      "title": "SunSare Aspirateur Balai sans Fil, 600W/50KPA/65Mins Aspirateur sans Fil Puissant avec Pliable Adaptateur, Tuyau 1M, Parfumé, Chargement Mural, Aspirateur Balai pour Poils d’Animaux/Sols/Tapis",
      "price": 179.99,
      "price_original": 189.99,
      "images": [
        "https://m.media-amazon.com/images/I/71qeciA31bL._AC_SL1500_.jpg",
        "https://m.media-amazon.com/images/I/41zsGfuydwL.jpg",
        "https://m.media-amazon.com/images/I/51vXTsRKa8L.jpg",
        "https://m.media-amazon.com/images/I/41Y-PryVwCL.jpg",
        "https://m.media-amazon.com/images/I/41oSC4IEcgL.jpg",
        "https://m.media-amazon.com/images/I/41ya+f0n03L.jpg",
        "https://m.media-amazon.com/images/I/51+bxBsse8L.jpg"
      ],
      "triggers": {
        "rating": 4.8,
        "reviews_count": 290,
        "discount_percent": 5,
        "original_price": 189.99,
        "discount_amount": 10,
        "has_prime": true
      },
      "score": 4.0,
      "deal_number": 18,
      "deal_id": "#018"
    },
    {
      "asin": "B0DT493J7J",
      "url": "https://www.amazon.fr/dp/B0DT493J7J",
      "title_preview": "",
      "price_flash": "Prix Flash: 56,90 €",
      "original_price": "Le plus bas : 61,66 €",
      "discount_text": "",
      "category": "Rasage et épilation",
      "has_prime": false,
      "title": "Gillette Lot De 20 Recharges De Rasoir Pour Hommes Proglide, AUTHENTIQUES, Cartouche A 5 Lames Ultra-Affutées, Nouvelle Lubrification, Bande Lubrifiante x2, Rasage Du Visage Flexible",
      "price": 56.9,
      "price_original": 61.66,
      "images": [
        "https://m.media-amazon.com/images/I/71z3LW5SjOL._AC_SL1500_.jpg",
        "https://m.media-amazon.com/images/I/41ZDH7CHNyL.jpg",
        "https://m.media-amazon.com/images/I/41etcejAa4L.jpg",
        "https://m.media-amazon.com/images/I/511SvYkf0TL.jpg",
        "https://m.media-amazon.com/images/I/41kPY1-sc3L.jpg",
        "https://m.media-amazon.com/images/I/51qrx3-0q2L.jpg",
        "https://m.media-amazon.com/images/I/41djUQhlFTL.jpg",
        "https://m.media-amazon.com/images/I/51owtod6IYL.jpg"
      ],
      "triggers": {
        "rating": 4.6,
        "reviews_count": 871,
        "discount_percent": 8,
        "original_price": 61.66,
        "discount_amount": 4.76,
        "has_prime": true
      },
      "score": 4.0,
      "deal_number": 19,
      "deal_id": "#019"
    },
    {
      "asin": "B08BQXK62C",
      "url": "https://www.amazon.fr/dp/B08BQXK62C",
      "title_preview": "",
      "price_flash": "Prix Flash: 679,79 €",
      "original_price": "Le plus bas : 759,90 €",
      "discount_text": "",
      "category": "Mobilier de jardin",
      "has_prime": false,
      "title": "tectake® Ensemble de 4 Fauteuils Confortables avec Accoudoirs, Salon de Jardin Exterieur ou Intérieur, PolyRotin et Aluminium, Coussins Inclus, Mobilier de Jardin Amenagement Balcon Terrasse Veranda",
      "price": 679.79,
      "price_original": 759.9,
      "images": [
        "https://m.media-amazon.com/images/I/81jOjDCPwsL._AC_SL1350_.jpg",
        "https://m.media-amazon.com/images/I/51T7WOLKF6L.jpg",
        "https://m.media-amazon.com/images/I/51KoALCFQFL.jpg",
        "https://m.media-amazon.com/images/I/41ODoSeYvlL.jpg",
        "https://m.media-amazon.com/images/I/51EbkvXdwdL.jpg",
        "https://m.media-amazon.com/images/I/41trrPEXBDL.jpg",
        "https://m.media-amazon.com/images/I/51POCSS7w6L.jpg",
        "https://m.media-amazon.com/images/I/51ipY7b8J4L.jpg"
      ],
      "triggers": {
        "rating": 4.4,
        "reviews_count": 147,
        "discount_percent": 11,
        "original_price": 759.9,
        "discount_amount": 80.11,
        "has_prime": true
      },
      "score": 4.0,
      "deal_number": 20,
      "deal_id": "#020"
    },
    {
      "asin": "B0FMY1NP6T",
      "url": "https://www.amazon.fr/dp/B0FMY1NP6T",
      "title_preview": "",
      "price_flash": "Prix Flash: 123,49 €",
      "original_price": "Le plus bas : 129,99 €",
      "discount_text": "",
      "category": "Piscines, bains à remous et accessoires",
      "has_prime": false,
      "title": "WINNY POOL CLEANER Winny 200 Robot Piscine, Aspirateur Piscine sans Fil avec Batterie, Autonomie 75 Min pour Piscines Hors-Sol 60m², Double Filtration,Stationnement Automatique(Transparent Noir)",
      "price": 123.49,
      "price_original": 129.99,
      "images": [
        "https://m.media-amazon.com/images/I/71pRFPjIRXL._AC_SL1500_.jpg",
        "https://m.media-amazon.com/images/I/41pXJF5Nm8L.jpg",
        "https://m.media-amazon.com/images/I/51FS7nPvDWL.jpg",
        "https://m.media-amazon.com/images/I/51t73Jdp+KL.jpg",
        "https://m.media-amazon.com/images/I/51PJkO5SOqL.jpg",
        "https://m.media-amazon.com/images/I/512r9dl8JML.jpg",
        "https://m.media-amazon.com/images/I/5137czlCOnL.jpg"
      ],
      "triggers": {
        "rating": 4.6,
        "reviews_count": 322,
        "discount_percent": 5,
        "original_price": 129.99,
        "discount_amount": 6.5,
        "has_prime": true
      },
      "score": 4.0,
      "deal_number": 21,
      "deal_id": "#021"
    },
    {
      "asin": "B0G381QW1X",
      "url": "https://www.amazon.fr/dp/B0G381QW1X",
      "title_preview": "",
      "price_flash": "Prix Flash: 94,99 €",
      "original_price": "Le plus bas : 99,99 €",
      "discount_text": "",
      "category": "Imprimantes et accessoires",
      "has_prime": false,
      "title": "Cartouche 937XL 937 9730e Compatible pour HP 937 Pack de 4 Cartouche XL 937e pour HP OfficeJet Pro 9730e 9120e 9720e 9132e 9122e 9120b 9125e 9130b 9130e 9720 9730 Imprimantes (Noir Cyan Jaune Magenta)",
      "price": 94.99,
      "price_original": 99.99,
      "images": [
        "https://m.media-amazon.com/images/I/71e35Sb2N7L._AC_SL1500_.jpg",
        "https://m.media-amazon.com/images/I/51aDMwvPViL.jpg",
        "https://m.media-amazon.com/images/I/41X2BKlj4EL.jpg",
        "https://m.media-amazon.com/images/I/51pf7VKZZNL.jpg",
        "https://m.media-amazon.com/images/I/41Xn4SVLtfL.jpg",
        "https://m.media-amazon.com/images/I/51aE2q7Aq1L.jpg",
        "https://m.media-amazon.com/images/I/41hihKVgjBL.jpg",
        "https://m.media-amazon.com/images/I/51VsCF1QOXL.SS40_BG85,85,85_BR-120_PKdp-play-icon-overlay__.jpg"
      ],
      "triggers": {
        "rating": 4.6,
        "reviews_count": 66,
        "discount_percent": 5,
        "original_price": 99.99,
        "discount_amount": 5,
        "has_prime": true
      },
      "score": 3.5,
      "deal_number": 22,
      "deal_id": "#022"
    },
    {
      "asin": "B0G4CQ2JCD",
      "url": "https://www.amazon.fr/dp/B0G4CQ2JCD",
      "title_preview": "",
      "price_flash": "Prix Flash: 370,49 €",
      "original_price": "Le plus bas : 459,99 €",
      "discount_text": "",
      "category": "Ordinateurs portables",
      "has_prime": false,
      "title": "18,5\" PC Portable, FHD Ordinateur Portable Processeur Quad-Core 13ème N150 Jusqu'à 3,60GHz, 16GB RAM + 512GB SSD M.2, Wi-FI Dual-Band, BT 5.2, USB 3.2, HDMI, Type-C, Batterie Longue 8000mAh",
      "price": 370.49,
      "price_original": 459.99,
      "images": [
        "https://m.media-amazon.com/images/I/71za5XiEdKL._AC_SL1500_.jpg",
        "https://m.media-amazon.com/images/I/51UfKtrOtzL.jpg",
        "https://m.media-amazon.com/images/I/51cXFTo+i6L.jpg",
        "https://m.media-amazon.com/images/I/51XEphae5vL.jpg",
        "https://m.media-amazon.com/images/I/41ugzvzFsYL.jpg",
        "https://m.media-amazon.com/images/I/41zprFmeEXL.jpg",
        "https://m.media-amazon.com/images/I/41xTqk68teL.jpg",
        "https://m.media-amazon.com/images/I/51MLi2q6ijL.SS40_BG85,85,85_BR-120_PKdp-play-icon-overlay__.jpg"
      ],
      "triggers": {
        "rating": 4.4,
        "reviews_count": 13,
        "discount_percent": 19,
        "original_price": 459.99,
        "discount_amount": 89.5,
        "has_prime": true
      },
      "score": 3.5,
      "deal_number": 23,
      "deal_id": "#023"
    },
    {
      "asin": "B0D5PR4VJ5",
      "url": "https://www.amazon.fr/dp/B0D5PR4VJ5",
      "title_preview": "",
      "price_flash": "Prix Flash: 75,99 €",
      "original_price": "Le plus bas : 79,99 €",
      "discount_text": "",
      "category": "Ameublement et décoration",
      "has_prime": false,
      "title": "EUGAD Lot de 2 Tabourets de Cuisine Haut, Tabouret de Bar Rond à Hauteur Réglable, Pivotant, avec Repose-Pieds, Siège Rembourré en Similucuir Vintage, Marron, 1085BY-2",
      "price": 75.99,
      "price_original": 79.99,
      "images": [
        "https://m.media-amazon.com/images/I/61YfElBIwgL._AC_SL1500_.jpg",
        "https://m.media-amazon.com/images/I/41mDZMQ5fNL.jpg",
        "https://m.media-amazon.com/images/I/51XAB8QBCFL.jpg",
        "https://m.media-amazon.com/images/I/41gVomE6RBL.jpg",
        "https://m.media-amazon.com/images/I/41227VO3HmL.jpg",
        "https://m.media-amazon.com/images/I/41knBLZOLVL.jpg",
        "https://m.media-amazon.com/images/I/51iqWsjSG-L.jpg",
        "https://m.media-amazon.com/images/I/51jbPA7rCnL.jpg"
      ],
      "triggers": {
        "rating": 4.6,
        "reviews_count": 96,
        "discount_percent": 5,
        "original_price": 79.99,
        "discount_amount": 4,
        "has_prime": true
      },
      "score": 3.5,
      "deal_number": 24,
      "deal_id": "#024"
    },
    {
      "asin": "B096W8645Q",
      "url": "https://www.amazon.fr/dp/B096W8645Q",
      "title_preview": "",
      "price_flash": "Prix Flash: 79,34 €",
      "original_price": "Le plus bas : 83,52 €",
      "discount_text": "",
      "category": "Produits professionnels de sécurité et de santé",
      "has_prime": false,
      "title": "SPC® by Brady Kit Anti-Pollution Chimique – Kit Absorbant Chimique pour Déversements de Produits Chimiques Dangereux, Inclus 10 Feuilles Absorbantes Chimiques, 2 Boudins, Gants et Sac de Déchet",
      "price": 79.34,
      "price_original": 83.52,
      "images": [
        "https://m.media-amazon.com/images/I/81MFQSw5mUL._AC_SL1500_.jpg",
        "https://m.media-amazon.com/images/I/41iqsv2AW6L.jpg",
        "https://m.media-amazon.com/images/I/41M2xXJ1nXL.jpg",
        "https://m.media-amazon.com/images/I/51cwDaXmvCL.jpg"
      ],
      "triggers": {
        "rating": 4.8,
        "reviews_count": 6,
        "discount_percent": 5,
        "original_price": 83.52,
        "discount_amount": 4.18,
        "has_prime": true
      },
      "score": 3.0,
      "deal_number": 25,
      "deal_id": "#025"
    }
  ]
}